{
  "schemaVersion": 1,
  "transcriptId": "c-yXhTmSSro",
  "model": "jackboyla/glirel-large-v0",
  "modelVersion": null,
  "predicatesUsed": [
    "works_for",
    "founded",
    "member_of",
    "led_by",
    "located_in",
    "born_in",
    "died_in",
    "operates_in",
    "met_with",
    "allied_with",
    "opposed_by",
    "funded_by",
    "accused_of",
    "investigated_by",
    "prosecuted_by",
    "convicted_of",
    "said",
    "believes",
    "endorses",
    "denies",
    "authored",
    "created",
    "published",
    "influenced_by",
    "part_of",
    "succeeded_by",
    "occurred_on",
    "caused",
    "resulted_in"
  ],
  "generatedAt": "2026-04-15T10:11:58.057Z",
  "edges": [
    {
      "id": "r_0001",
      "predicate": "funded_by",
      "subjectMentionId": "m_0001",
      "objectMentionId": "m_0002",
      "score": 0.33683809638023376,
      "evidence": {
        "transcriptId": "c-yXhTmSSro",
        "charStart": 0,
        "charEnd": 499,
        "timeStart": 8.32,
        "timeEnd": 54.399
      }
    },
    {
      "id": "r_0002",
      "predicate": "met_with",
      "subjectMentionId": "m_0002",
      "objectMentionId": "m_0004",
      "score": 0.32808828353881836,
      "evidence": {
        "transcriptId": "c-yXhTmSSro",
        "charStart": 0,
        "charEnd": 499,
        "timeStart": 8.32,
        "timeEnd": 54.399
      }
    },
    {
      "id": "r_0003",
      "predicate": "funded_by",
      "subjectMentionId": "m_0002",
      "objectMentionId": "m_0001",
      "score": 0.30012214183807373,
      "evidence": {
        "transcriptId": "c-yXhTmSSro",
        "charStart": 0,
        "charEnd": 499,
        "timeStart": 8.32,
        "timeEnd": 54.399
      }
    },
    {
      "id": "r_0004",
      "predicate": "member_of",
      "subjectMentionId": "m_0023",
      "objectMentionId": "m_0022",
      "score": 0.43880560994148254,
      "evidence": {
        "transcriptId": "c-yXhTmSSro",
        "charStart": 1460,
        "charEnd": 1933,
        "timeStart": 108.079,
        "timeEnd": 135.599
      }
    },
    {
      "id": "r_0005",
      "predicate": "member_of",
      "subjectMentionId": "m_0022",
      "objectMentionId": "m_0023",
      "score": 0.4229288697242737,
      "evidence": {
        "transcriptId": "c-yXhTmSSro",
        "charStart": 1460,
        "charEnd": 1933,
        "timeStart": 108.079,
        "timeEnd": 135.599
      }
    },
    {
      "id": "r_0006",
      "predicate": "part_of",
      "subjectMentionId": "m_0020",
      "objectMentionId": "m_0023",
      "score": 0.4127380847930908,
      "evidence": {
        "transcriptId": "c-yXhTmSSro",
        "charStart": 1460,
        "charEnd": 1933,
        "timeStart": 108.079,
        "timeEnd": 135.599
      }
    },
    {
      "id": "r_0007",
      "predicate": "member_of",
      "subjectMentionId": "m_0023",
      "objectMentionId": "m_0021",
      "score": 0.4064018428325653,
      "evidence": {
        "transcriptId": "c-yXhTmSSro",
        "charStart": 1460,
        "charEnd": 1933,
        "timeStart": 108.079,
        "timeEnd": 135.599
      }
    },
    {
      "id": "r_0008",
      "predicate": "part_of",
      "subjectMentionId": "m_0023",
      "objectMentionId": "m_0020",
      "score": 0.40278229117393494,
      "evidence": {
        "transcriptId": "c-yXhTmSSro",
        "charStart": 1460,
        "charEnd": 1933,
        "timeStart": 108.079,
        "timeEnd": 135.599
      }
    },
    {
      "id": "r_0009",
      "predicate": "member_of",
      "subjectMentionId": "m_0021",
      "objectMentionId": "m_0023",
      "score": 0.3867590129375458,
      "evidence": {
        "transcriptId": "c-yXhTmSSro",
        "charStart": 1460,
        "charEnd": 1933,
        "timeStart": 108.079,
        "timeEnd": 135.599
      }
    },
    {
      "id": "r_0010",
      "predicate": "member_of",
      "subjectMentionId": "m_0022",
      "objectMentionId": "m_0021",
      "score": 0.33411064743995667,
      "evidence": {
        "transcriptId": "c-yXhTmSSro",
        "charStart": 1460,
        "charEnd": 1933,
        "timeStart": 108.079,
        "timeEnd": 135.599
      }
    },
    {
      "id": "r_0011",
      "predicate": "member_of",
      "subjectMentionId": "m_0021",
      "objectMentionId": "m_0022",
      "score": 0.33073917031288147,
      "evidence": {
        "transcriptId": "c-yXhTmSSro",
        "charStart": 1460,
        "charEnd": 1933,
        "timeStart": 108.079,
        "timeEnd": 135.599
      }
    },
    {
      "id": "r_0012",
      "predicate": "member_of",
      "subjectMentionId": "m_0022",
      "objectMentionId": "m_0020",
      "score": 0.3197259306907654,
      "evidence": {
        "transcriptId": "c-yXhTmSSro",
        "charStart": 1460,
        "charEnd": 1933,
        "timeStart": 108.079,
        "timeEnd": 135.599
      }
    },
    {
      "id": "r_0013",
      "predicate": "member_of",
      "subjectMentionId": "m_0020",
      "objectMentionId": "m_0022",
      "score": 0.31942909955978394,
      "evidence": {
        "transcriptId": "c-yXhTmSSro",
        "charStart": 1460,
        "charEnd": 1933,
        "timeStart": 108.079,
        "timeEnd": 135.599
      }
    },
    {
      "id": "r_0014",
      "predicate": "located_in",
      "subjectMentionId": "m_0115",
      "objectMentionId": "m_0117",
      "score": 0.3433898687362671,
      "evidence": {
        "transcriptId": "c-yXhTmSSro",
        "charStart": 9246,
        "charEnd": 9745,
        "timeStart": 702.8,
        "timeEnd": 735.36
      }
    },
    {
      "id": "r_0015",
      "predicate": "located_in",
      "subjectMentionId": "m_0115",
      "objectMentionId": "m_0114",
      "score": 0.3128494322299957,
      "evidence": {
        "transcriptId": "c-yXhTmSSro",
        "charStart": 9246,
        "charEnd": 9745,
        "timeStart": 702.8,
        "timeEnd": 735.36
      }
    },
    {
      "id": "r_0016",
      "predicate": "located_in",
      "subjectMentionId": "m_0115",
      "objectMentionId": "m_0116",
      "score": 0.307932585477829,
      "evidence": {
        "transcriptId": "c-yXhTmSSro",
        "charStart": 9246,
        "charEnd": 9745,
        "timeStart": 702.8,
        "timeEnd": 735.36
      }
    },
    {
      "id": "r_0017",
      "predicate": "located_in",
      "subjectMentionId": "m_0114",
      "objectMentionId": "m_0117",
      "score": 0.30110692977905273,
      "evidence": {
        "transcriptId": "c-yXhTmSSro",
        "charStart": 9246,
        "charEnd": 9745,
        "timeStart": 702.8,
        "timeEnd": 735.36
      }
    },
    {
      "id": "r_0018",
      "predicate": "located_in",
      "subjectMentionId": "m_0139",
      "objectMentionId": "m_0142",
      "score": 0.39389798045158386,
      "evidence": {
        "transcriptId": "c-yXhTmSSro",
        "charStart": 11207,
        "charEnd": 11687,
        "timeStart": 831.68,
        "timeEnd": 857.6
      }
    },
    {
      "id": "r_0019",
      "predicate": "located_in",
      "subjectMentionId": "m_0140",
      "objectMentionId": "m_0142",
      "score": 0.3739345967769623,
      "evidence": {
        "transcriptId": "c-yXhTmSSro",
        "charStart": 11207,
        "charEnd": 11687,
        "timeStart": 831.68,
        "timeEnd": 857.6
      }
    },
    {
      "id": "r_0020",
      "predicate": "part_of",
      "subjectMentionId": "m_0142",
      "objectMentionId": "m_0139",
      "score": 0.3556634783744812,
      "evidence": {
        "transcriptId": "c-yXhTmSSro",
        "charStart": 11207,
        "charEnd": 11687,
        "timeStart": 831.68,
        "timeEnd": 857.6
      }
    },
    {
      "id": "r_0021",
      "predicate": "located_in",
      "subjectMentionId": "m_0143",
      "objectMentionId": "m_0142",
      "score": 0.3507893979549408,
      "evidence": {
        "transcriptId": "c-yXhTmSSro",
        "charStart": 11207,
        "charEnd": 11687,
        "timeStart": 831.68,
        "timeEnd": 857.6
      }
    },
    {
      "id": "r_0022",
      "predicate": "located_in",
      "subjectMentionId": "m_0141",
      "objectMentionId": "m_0142",
      "score": 0.3442981541156769,
      "evidence": {
        "transcriptId": "c-yXhTmSSro",
        "charStart": 11207,
        "charEnd": 11687,
        "timeStart": 831.68,
        "timeEnd": 857.6
      }
    },
    {
      "id": "r_0023",
      "predicate": "caused",
      "subjectMentionId": "m_0163",
      "objectMentionId": "m_0161",
      "score": 0.31688109040260315,
      "evidence": {
        "transcriptId": "c-yXhTmSSro",
        "charStart": 13113,
        "charEnd": 13612,
        "timeStart": 968.72,
        "timeEnd": 1036.319
      }
    },
    {
      "id": "r_0024",
      "predicate": "located_in",
      "subjectMentionId": "m_0171",
      "objectMentionId": "m_0168",
      "score": 0.38512346148490906,
      "evidence": {
        "transcriptId": "c-yXhTmSSro",
        "charStart": 13612,
        "charEnd": 14081,
        "timeStart": 1034.559,
        "timeEnd": 1083.76
      }
    },
    {
      "id": "r_0025",
      "predicate": "located_in",
      "subjectMentionId": "m_0168",
      "objectMentionId": "m_0171",
      "score": 0.3450997769832611,
      "evidence": {
        "transcriptId": "c-yXhTmSSro",
        "charStart": 13612,
        "charEnd": 14081,
        "timeStart": 1034.559,
        "timeEnd": 1083.76
      }
    },
    {
      "id": "r_0026",
      "predicate": "part_of",
      "subjectMentionId": "m_0283",
      "objectMentionId": "m_0286",
      "score": 0.3474949896335602,
      "evidence": {
        "transcriptId": "c-yXhTmSSro",
        "charStart": 22832,
        "charEnd": 23327,
        "timeStart": 1782.08,
        "timeEnd": 1828.559
      }
    },
    {
      "id": "r_0027",
      "predicate": "part_of",
      "subjectMentionId": "m_0286",
      "objectMentionId": "m_0283",
      "score": 0.31556612253189087,
      "evidence": {
        "transcriptId": "c-yXhTmSSro",
        "charStart": 22832,
        "charEnd": 23327,
        "timeStart": 1782.08,
        "timeEnd": 1828.559
      }
    },
    {
      "id": "r_0028",
      "predicate": "part_of",
      "subjectMentionId": "m_0298",
      "objectMentionId": "m_0299",
      "score": 0.3082267642021179,
      "evidence": {
        "transcriptId": "c-yXhTmSSro",
        "charStart": 23797,
        "charEnd": 24292,
        "timeStart": 1887.6,
        "timeEnd": 1926.799
      }
    },
    {
      "id": "r_0029",
      "predicate": "part_of",
      "subjectMentionId": "m_0299",
      "objectMentionId": "m_0298",
      "score": 0.3060530722141266,
      "evidence": {
        "transcriptId": "c-yXhTmSSro",
        "charStart": 23797,
        "charEnd": 24292,
        "timeStart": 1887.6,
        "timeEnd": 1926.799
      }
    },
    {
      "id": "r_0030",
      "predicate": "part_of",
      "subjectMentionId": "m_0299",
      "objectMentionId": "m_0297",
      "score": 0.30076417326927185,
      "evidence": {
        "transcriptId": "c-yXhTmSSro",
        "charStart": 23797,
        "charEnd": 24292,
        "timeStart": 1887.6,
        "timeEnd": 1926.799
      }
    },
    {
      "id": "r_0031",
      "predicate": "located_in",
      "subjectMentionId": "m_0347",
      "objectMentionId": "m_0350",
      "score": 0.39049386978149414,
      "evidence": {
        "transcriptId": "c-yXhTmSSro",
        "charStart": 27703,
        "charEnd": 28186,
        "timeStart": 2213.359,
        "timeEnd": 2262.079
      }
    },
    {
      "id": "r_0032",
      "predicate": "part_of",
      "subjectMentionId": "m_0350",
      "objectMentionId": "m_0346",
      "score": 0.386710524559021,
      "evidence": {
        "transcriptId": "c-yXhTmSSro",
        "charStart": 27703,
        "charEnd": 28186,
        "timeStart": 2213.359,
        "timeEnd": 2262.079
      }
    },
    {
      "id": "r_0033",
      "predicate": "part_of",
      "subjectMentionId": "m_0346",
      "objectMentionId": "m_0350",
      "score": 0.37846389412879944,
      "evidence": {
        "transcriptId": "c-yXhTmSSro",
        "charStart": 27703,
        "charEnd": 28186,
        "timeStart": 2213.359,
        "timeEnd": 2262.079
      }
    },
    {
      "id": "r_0034",
      "predicate": "part_of",
      "subjectMentionId": "m_0350",
      "objectMentionId": "m_0347",
      "score": 0.3644409775733948,
      "evidence": {
        "transcriptId": "c-yXhTmSSro",
        "charStart": 27703,
        "charEnd": 28186,
        "timeStart": 2213.359,
        "timeEnd": 2262.079
      }
    },
    {
      "id": "r_0035",
      "predicate": "located_in",
      "subjectMentionId": "m_0355",
      "objectMentionId": "m_0356",
      "score": 0.3049095571041107,
      "evidence": {
        "transcriptId": "c-yXhTmSSro",
        "charStart": 28187,
        "charEnd": 28667,
        "timeStart": 2258,
        "timeEnd": 2309.599
      }
    },
    {
      "id": "r_0036",
      "predicate": "member_of",
      "subjectMentionId": "m_0362",
      "objectMentionId": "m_0361",
      "score": 0.304171621799469,
      "evidence": {
        "transcriptId": "c-yXhTmSSro",
        "charStart": 28187,
        "charEnd": 28667,
        "timeStart": 2258,
        "timeEnd": 2309.599
      }
    },
    {
      "id": "r_0037",
      "predicate": "member_of",
      "subjectMentionId": "m_0361",
      "objectMentionId": "m_0362",
      "score": 0.3024529218673706,
      "evidence": {
        "transcriptId": "c-yXhTmSSro",
        "charStart": 28187,
        "charEnd": 28667,
        "timeStart": 2258,
        "timeEnd": 2309.599
      }
    },
    {
      "id": "r_0038",
      "predicate": "member_of",
      "subjectMentionId": "m_0398",
      "objectMentionId": "m_0399",
      "score": 0.5152532458305359,
      "evidence": {
        "transcriptId": "c-yXhTmSSro",
        "charStart": 31102,
        "charEnd": 31596,
        "timeStart": 2510.48,
        "timeEnd": 2570.079
      }
    },
    {
      "id": "r_0039",
      "predicate": "member_of",
      "subjectMentionId": "m_0399",
      "objectMentionId": "m_0398",
      "score": 0.5106695890426636,
      "evidence": {
        "transcriptId": "c-yXhTmSSro",
        "charStart": 31102,
        "charEnd": 31596,
        "timeStart": 2510.48,
        "timeEnd": 2570.079
      }
    },
    {
      "id": "r_0040",
      "predicate": "located_in",
      "subjectMentionId": "m_0396",
      "objectMentionId": "m_0400",
      "score": 0.43141359090805054,
      "evidence": {
        "transcriptId": "c-yXhTmSSro",
        "charStart": 31102,
        "charEnd": 31596,
        "timeStart": 2510.48,
        "timeEnd": 2570.079
      }
    },
    {
      "id": "r_0041",
      "predicate": "located_in",
      "subjectMentionId": "m_0401",
      "objectMentionId": "m_0400",
      "score": 0.4235907793045044,
      "evidence": {
        "transcriptId": "c-yXhTmSSro",
        "charStart": 31102,
        "charEnd": 31596,
        "timeStart": 2510.48,
        "timeEnd": 2570.079
      }
    },
    {
      "id": "r_0042",
      "predicate": "located_in",
      "subjectMentionId": "m_0400",
      "objectMentionId": "m_0401",
      "score": 0.4016193151473999,
      "evidence": {
        "transcriptId": "c-yXhTmSSro",
        "charStart": 31102,
        "charEnd": 31596,
        "timeStart": 2510.48,
        "timeEnd": 2570.079
      }
    },
    {
      "id": "r_0043",
      "predicate": "member_of",
      "subjectMentionId": "m_0396",
      "objectMentionId": "m_0399",
      "score": 0.38488197326660156,
      "evidence": {
        "transcriptId": "c-yXhTmSSro",
        "charStart": 31102,
        "charEnd": 31596,
        "timeStart": 2510.48,
        "timeEnd": 2570.079
      }
    },
    {
      "id": "r_0044",
      "predicate": "located_in",
      "subjectMentionId": "m_0400",
      "objectMentionId": "m_0396",
      "score": 0.37350237369537354,
      "evidence": {
        "transcriptId": "c-yXhTmSSro",
        "charStart": 31102,
        "charEnd": 31596,
        "timeStart": 2510.48,
        "timeEnd": 2570.079
      }
    },
    {
      "id": "r_0045",
      "predicate": "member_of",
      "subjectMentionId": "m_0401",
      "objectMentionId": "m_0399",
      "score": 0.34769734740257263,
      "evidence": {
        "transcriptId": "c-yXhTmSSro",
        "charStart": 31102,
        "charEnd": 31596,
        "timeStart": 2510.48,
        "timeEnd": 2570.079
      }
    },
    {
      "id": "r_0046",
      "predicate": "operates_in",
      "subjectMentionId": "m_0446",
      "objectMentionId": "m_0447",
      "score": 0.3376774191856384,
      "evidence": {
        "transcriptId": "c-yXhTmSSro",
        "charStart": 35520,
        "charEnd": 36011,
        "timeStart": 2875.28,
        "timeEnd": 2905.4399999999996
      }
    },
    {
      "id": "r_0047",
      "predicate": "operates_in",
      "subjectMentionId": "m_0447",
      "objectMentionId": "m_0446",
      "score": 0.33137741684913635,
      "evidence": {
        "transcriptId": "c-yXhTmSSro",
        "charStart": 35520,
        "charEnd": 36011,
        "timeStart": 2875.28,
        "timeEnd": 2905.4399999999996
      }
    },
    {
      "id": "r_0048",
      "predicate": "operates_in",
      "subjectMentionId": "m_0448",
      "objectMentionId": "m_0446",
      "score": 0.3172769546508789,
      "evidence": {
        "transcriptId": "c-yXhTmSSro",
        "charStart": 35520,
        "charEnd": 36011,
        "timeStart": 2875.28,
        "timeEnd": 2905.4399999999996
      }
    },
    {
      "id": "r_0049",
      "predicate": "operates_in",
      "subjectMentionId": "m_0446",
      "objectMentionId": "m_0448",
      "score": 0.30123111605644226,
      "evidence": {
        "transcriptId": "c-yXhTmSSro",
        "charStart": 35520,
        "charEnd": 36011,
        "timeStart": 2875.28,
        "timeEnd": 2905.4399999999996
      }
    },
    {
      "id": "r_0050",
      "predicate": "member_of",
      "subjectMentionId": "m_0457",
      "objectMentionId": "m_0454",
      "score": 0.3821841776371002,
      "evidence": {
        "transcriptId": "c-yXhTmSSro",
        "charStart": 36507,
        "charEnd": 37005,
        "timeStart": 2922.72,
        "timeEnd": 2951.119
      }
    },
    {
      "id": "r_0051",
      "predicate": "member_of",
      "subjectMentionId": "m_0454",
      "objectMentionId": "m_0457",
      "score": 0.3579915165901184,
      "evidence": {
        "transcriptId": "c-yXhTmSSro",
        "charStart": 36507,
        "charEnd": 37005,
        "timeStart": 2922.72,
        "timeEnd": 2951.119
      }
    },
    {
      "id": "r_0052",
      "predicate": "funded_by",
      "subjectMentionId": "m_0455",
      "objectMentionId": "m_0454",
      "score": 0.35454657673835754,
      "evidence": {
        "transcriptId": "c-yXhTmSSro",
        "charStart": 36507,
        "charEnd": 37005,
        "timeStart": 2922.72,
        "timeEnd": 2951.119
      }
    },
    {
      "id": "r_0053",
      "predicate": "member_of",
      "subjectMentionId": "m_0457",
      "objectMentionId": "m_0458",
      "score": 0.34201425313949585,
      "evidence": {
        "transcriptId": "c-yXhTmSSro",
        "charStart": 36507,
        "charEnd": 37005,
        "timeStart": 2922.72,
        "timeEnd": 2951.119
      }
    },
    {
      "id": "r_0054",
      "predicate": "funded_by",
      "subjectMentionId": "m_0456",
      "objectMentionId": "m_0454",
      "score": 0.33835625648498535,
      "evidence": {
        "transcriptId": "c-yXhTmSSro",
        "charStart": 36507,
        "charEnd": 37005,
        "timeStart": 2922.72,
        "timeEnd": 2951.119
      }
    },
    {
      "id": "r_0055",
      "predicate": "member_of",
      "subjectMentionId": "m_0458",
      "objectMentionId": "m_0457",
      "score": 0.3355313241481781,
      "evidence": {
        "transcriptId": "c-yXhTmSSro",
        "charStart": 36507,
        "charEnd": 37005,
        "timeStart": 2922.72,
        "timeEnd": 2951.119
      }
    },
    {
      "id": "r_0056",
      "predicate": "funded_by",
      "subjectMentionId": "m_0453",
      "objectMentionId": "m_0454",
      "score": 0.32125404477119446,
      "evidence": {
        "transcriptId": "c-yXhTmSSro",
        "charStart": 36507,
        "charEnd": 37005,
        "timeStart": 2922.72,
        "timeEnd": 2951.119
      }
    },
    {
      "id": "r_0057",
      "predicate": "member_of",
      "subjectMentionId": "m_0467",
      "objectMentionId": "m_0465",
      "score": 0.48784971237182617,
      "evidence": {
        "transcriptId": "c-yXhTmSSro",
        "charStart": 37931,
        "charEnd": 38395,
        "timeStart": 2995.2,
        "timeEnd": 3020.319
      }
    },
    {
      "id": "r_0058",
      "predicate": "member_of",
      "subjectMentionId": "m_0467",
      "objectMentionId": "m_0466",
      "score": 0.39221447706222534,
      "evidence": {
        "transcriptId": "c-yXhTmSSro",
        "charStart": 37931,
        "charEnd": 38395,
        "timeStart": 2995.2,
        "timeEnd": 3020.319
      }
    },
    {
      "id": "r_0059",
      "predicate": "member_of",
      "subjectMentionId": "m_0465",
      "objectMentionId": "m_0467",
      "score": 0.3168920874595642,
      "evidence": {
        "transcriptId": "c-yXhTmSSro",
        "charStart": 37931,
        "charEnd": 38395,
        "timeStart": 2995.2,
        "timeEnd": 3020.319
      }
    }
  ]
}