{
  "version": 1,
  "entities": {
    "person:galway ireland": {
      "id": "person:galway ireland",
      "type": "person",
      "canonical": "Galway Ireland",
      "aliases": [
        "Ireland",
        "her"
      ],
      "mentions": [
        {
          "transcriptId": "AOO5a_jUOzg",
          "charStart": 1113,
          "charEnd": 1127,
          "timeStart": 71,
          "timeEnd": 78
        },
        {
          "transcriptId": "AOO5a_jUOzg",
          "charStart": 4935,
          "charEnd": 4942,
          "timeStart": 302,
          "timeEnd": 310
        },
        {
          "transcriptId": "AOO5a_jUOzg",
          "charStart": 4965,
          "charEnd": 4968,
          "timeStart": 302,
          "timeEnd": 310
        },
        {
          "transcriptId": "AOO5a_jUOzg",
          "charStart": 4988,
          "charEnd": 4991,
          "timeStart": 302,
          "timeEnd": 310
        },
        {
          "transcriptId": "AOO5a_jUOzg",
          "charStart": 5054,
          "charEnd": 5057,
          "timeStart": 310,
          "timeEnd": 319
        },
        {
          "transcriptId": "AOO5a_jUOzg",
          "charStart": 5080,
          "charEnd": 5083,
          "timeStart": 310,
          "timeEnd": 319
        }
      ]
    },
    "person:michael faraday": {
      "id": "person:michael faraday",
      "type": "person",
      "canonical": "Michael Faraday",
      "aliases": [
        "Faraday",
        "his"
      ],
      "mentions": [
        {
          "transcriptId": "AOO5a_jUOzg",
          "charStart": 1140,
          "charEnd": 1155,
          "timeStart": 71,
          "timeEnd": 78
        },
        {
          "transcriptId": "AOO5a_jUOzg",
          "charStart": 1469,
          "charEnd": 1484,
          "timeStart": 87,
          "timeEnd": 94
        },
        {
          "transcriptId": "AOO5a_jUOzg",
          "charStart": 1387,
          "charEnd": 1394,
          "timeStart": 87,
          "timeEnd": 94
        },
        {
          "transcriptId": "AOO5a_jUOzg",
          "charStart": 1403,
          "charEnd": 1410,
          "timeStart": 87,
          "timeEnd": 94
        },
        {
          "transcriptId": "AOO5a_jUOzg",
          "charStart": 1529,
          "charEnd": 1532,
          "timeStart": 94,
          "timeEnd": 102
        },
        {
          "transcriptId": "AOO5a_jUOzg",
          "charStart": 1554,
          "charEnd": 1557,
          "timeStart": 94,
          "timeEnd": 102
        }
      ]
    },
    "person:professor bernard knight": {
      "id": "person:professor bernard knight",
      "type": "person",
      "canonical": "Professor Bernard Knight",
      "aliases": [],
      "mentions": [
        {
          "transcriptId": "AOO5a_jUOzg",
          "charStart": 1694,
          "charEnd": 1718,
          "timeStart": 102,
          "timeEnd": 111
        }
      ]
    },
    "person:knight": {
      "id": "person:knight",
      "type": "person",
      "canonical": "Knight",
      "aliases": [
        "Dr Knight"
      ],
      "mentions": [
        {
          "transcriptId": "AOO5a_jUOzg",
          "charStart": 1752,
          "charEnd": 1761,
          "timeStart": 102,
          "timeEnd": 111
        },
        {
          "transcriptId": "AOO5a_jUOzg",
          "charStart": 1752,
          "charEnd": 1761,
          "timeStart": 102,
          "timeEnd": 111
        }
      ]
    },
    "person:frank frank": {
      "id": "person:frank frank",
      "type": "person",
      "canonical": "Frank Frank",
      "aliases": [
        "he",
        "his",
        "she",
        "her"
      ],
      "mentions": [
        {
          "transcriptId": "AOO5a_jUOzg",
          "charStart": 2115,
          "charEnd": 2126,
          "timeStart": 125,
          "timeEnd": 133
        },
        {
          "transcriptId": "AOO5a_jUOzg",
          "charStart": 2175,
          "charEnd": 2177,
          "timeStart": 133,
          "timeEnd": 142
        },
        {
          "transcriptId": "AOO5a_jUOzg",
          "charStart": 2182,
          "charEnd": 2185,
          "timeStart": 133,
          "timeEnd": 142
        },
        {
          "transcriptId": "AOO5a_jUOzg",
          "charStart": 2240,
          "charEnd": 2243,
          "timeStart": 133,
          "timeEnd": 142
        },
        {
          "transcriptId": "AOO5a_jUOzg",
          "charStart": 2273,
          "charEnd": 2276,
          "timeStart": 133,
          "timeEnd": 142
        },
        {
          "transcriptId": "AOO5a_jUOzg",
          "charStart": 2368,
          "charEnd": 2371,
          "timeStart": 142,
          "timeEnd": 150
        },
        {
          "transcriptId": "AOO5a_jUOzg",
          "charStart": 2490,
          "charEnd": 2493,
          "timeStart": 150,
          "timeEnd": 157
        },
        {
          "transcriptId": "AOO5a_jUOzg",
          "charStart": 2514,
          "charEnd": 2517,
          "timeStart": 150,
          "timeEnd": 157
        },
        {
          "transcriptId": "AOO5a_jUOzg",
          "charStart": 2531,
          "charEnd": 2534,
          "timeStart": 150,
          "timeEnd": 157
        },
        {
          "transcriptId": "AOO5a_jUOzg",
          "charStart": 2544,
          "charEnd": 2547,
          "timeStart": 150,
          "timeEnd": 157
        },
        {
          "transcriptId": "AOO5a_jUOzg",
          "charStart": 2580,
          "charEnd": 2583,
          "timeStart": 157,
          "timeEnd": 166
        }
      ]
    },
    "person:nicole malay": {
      "id": "person:nicole malay",
      "type": "person",
      "canonical": "Nicole Malay",
      "aliases": [
        "Nicole",
        "her",
        "she"
      ],
      "mentions": [
        {
          "transcriptId": "AOO5a_jUOzg",
          "charStart": 3381,
          "charEnd": 3393,
          "timeStart": 209,
          "timeEnd": 218
        },
        {
          "transcriptId": "AOO5a_jUOzg",
          "charStart": 3622,
          "charEnd": 3628,
          "timeStart": 225,
          "timeEnd": 233
        },
        {
          "transcriptId": "AOO5a_jUOzg",
          "charStart": 3495,
          "charEnd": 3498,
          "timeStart": 218,
          "timeEnd": 225
        },
        {
          "transcriptId": "AOO5a_jUOzg",
          "charStart": 3521,
          "charEnd": 3524,
          "timeStart": 218,
          "timeEnd": 225
        },
        {
          "transcriptId": "AOO5a_jUOzg",
          "charStart": 3560,
          "charEnd": 3563,
          "timeStart": 218,
          "timeEnd": 225
        },
        {
          "transcriptId": "AOO5a_jUOzg",
          "charStart": 3671,
          "charEnd": 3674,
          "timeStart": 225,
          "timeEnd": 233
        }
      ]
    },
    "person:malay": {
      "id": "person:malay",
      "type": "person",
      "canonical": "Malay",
      "aliases": [
        "Mr Malay"
      ],
      "mentions": [
        {
          "transcriptId": "AOO5a_jUOzg",
          "charStart": 3682,
          "charEnd": 3690,
          "timeStart": 225,
          "timeEnd": 233
        },
        {
          "transcriptId": "AOO5a_jUOzg",
          "charStart": 3682,
          "charEnd": 3690,
          "timeStart": 225,
          "timeEnd": 233
        }
      ]
    },
    "person:italian countess": {
      "id": "person:italian countess",
      "type": "person",
      "canonical": "Italian Countess",
      "aliases": [
        "Italian",
        "he"
      ],
      "mentions": [
        {
          "transcriptId": "AOO5a_jUOzg",
          "charStart": 3800,
          "charEnd": 3816,
          "timeStart": 233,
          "timeEnd": 241
        },
        {
          "transcriptId": "AOO5a_jUOzg",
          "charStart": 3141,
          "charEnd": 3148,
          "timeStart": 191,
          "timeEnd": 200
        },
        {
          "transcriptId": "AOO5a_jUOzg",
          "charStart": 3258,
          "charEnd": 3260,
          "timeStart": 200,
          "timeEnd": 209
        },
        {
          "transcriptId": "AOO5a_jUOzg",
          "charStart": 3283,
          "charEnd": 3285,
          "timeStart": 200,
          "timeEnd": 209
        }
      ]
    },
    "person:phyllis newcomb": {
      "id": "person:phyllis newcomb",
      "type": "person",
      "canonical": "Phyllis Newcomb",
      "aliases": [],
      "mentions": [
        {
          "transcriptId": "AOO5a_jUOzg",
          "charStart": 4159,
          "charEnd": 4174,
          "timeStart": 258,
          "timeEnd": 267
        }
      ]
    },
    "person:shire hall": {
      "id": "person:shire hall",
      "type": "person",
      "canonical": "Shire Hall",
      "aliases": [],
      "mentions": [
        {
          "transcriptId": "AOO5a_jUOzg",
          "charStart": 4198,
          "charEnd": 4208,
          "timeStart": 258,
          "timeEnd": 267
        }
      ]
    },
    "person:john irving bentley": {
      "id": "person:john irving bentley",
      "type": "person",
      "canonical": "John Irving Bentley",
      "aliases": [
        "Dr John Irving Bentley"
      ],
      "mentions": [
        {
          "transcriptId": "AOO5a_jUOzg",
          "charStart": 4483,
          "charEnd": 4505,
          "timeStart": 276,
          "timeEnd": 284
        }
      ]
    },
    "person:danny van zant": {
      "id": "person:danny van zant",
      "type": "person",
      "canonical": "Danny Van Zant",
      "aliases": [
        "his"
      ],
      "mentions": [
        {
          "transcriptId": "AOO5a_jUOzg",
          "charStart": 5309,
          "charEnd": 5323,
          "timeStart": 328,
          "timeEnd": 336
        },
        {
          "transcriptId": "AOO5a_jUOzg",
          "charStart": 5401,
          "charEnd": 5404,
          "timeStart": 328,
          "timeEnd": 336
        }
      ]
    },
    "person:van zant": {
      "id": "person:van zant",
      "type": "person",
      "canonical": "Van Zant",
      "aliases": [],
      "mentions": [
        {
          "transcriptId": "AOO5a_jUOzg",
          "charStart": 5421,
          "charEnd": 5429,
          "timeStart": 336,
          "timeEnd": 343
        }
      ]
    },
    "person:sheriff ron lockhart": {
      "id": "person:sheriff ron lockhart",
      "type": "person",
      "canonical": "Sheriff Ron Lockhart",
      "aliases": [],
      "mentions": [
        {
          "transcriptId": "AOO5a_jUOzg",
          "charStart": 5477,
          "charEnd": 5497,
          "timeStart": 336,
          "timeEnd": 343
        }
      ]
    },
    "person:richard reeser": {
      "id": "person:richard reeser",
      "type": "person",
      "canonical": "Richard Reeser",
      "aliases": [
        "Dr Richard Reeser"
      ],
      "mentions": [
        {
          "transcriptId": "AOO5a_jUOzg",
          "charStart": 6219,
          "charEnd": 6236,
          "timeStart": 384,
          "timeEnd": 392
        }
      ]
    },
    "person:mary reeser mary": {
      "id": "person:mary reeser mary",
      "type": "person",
      "canonical": "Mary Reeser Mary",
      "aliases": [],
      "mentions": [
        {
          "transcriptId": "AOO5a_jUOzg",
          "charStart": 6261,
          "charEnd": 6277,
          "timeStart": 392,
          "timeEnd": 399
        }
      ]
    },
    "person:reds red devils": {
      "id": "person:reds red devils",
      "type": "person",
      "canonical": "Reds Red Devils",
      "aliases": [],
      "mentions": [
        {
          "transcriptId": "AOO5a_jUOzg",
          "charStart": 6514,
          "charEnd": 6529,
          "timeStart": 406,
          "timeEnd": 414
        }
      ]
    },
    "person:cardinals red hots pink ladies": {
      "id": "person:cardinals red hots pink ladies",
      "type": "person",
      "canonical": "Cardinals Red Hots Pink Ladies",
      "aliases": [
        "Ladies"
      ],
      "mentions": [
        {
          "transcriptId": "AOO5a_jUOzg",
          "charStart": 6584,
          "charEnd": 6614,
          "timeStart": 406,
          "timeEnd": 414
        },
        {
          "transcriptId": "AOO5a_jUOzg",
          "charStart": 19891,
          "charEnd": 19897,
          "timeStart": 1248,
          "timeEnd": 1256
        }
      ]
    },
    "person:mary reeser": {
      "id": "person:mary reeser",
      "type": "person",
      "canonical": "Mary Reeser",
      "aliases": [
        "she",
        "her"
      ],
      "mentions": [
        {
          "transcriptId": "AOO5a_jUOzg",
          "charStart": 6947,
          "charEnd": 6958,
          "timeStart": 431,
          "timeEnd": 439
        },
        {
          "transcriptId": "AOO5a_jUOzg",
          "charStart": 12507,
          "charEnd": 12518,
          "timeStart": 763,
          "timeEnd": 771
        },
        {
          "transcriptId": "AOO5a_jUOzg",
          "charStart": 13383,
          "charEnd": 13394,
          "timeStart": 812,
          "timeEnd": 821
        },
        {
          "transcriptId": "AOO5a_jUOzg",
          "charStart": 13422,
          "charEnd": 13425,
          "timeStart": 821,
          "timeEnd": 829
        },
        {
          "transcriptId": "AOO5a_jUOzg",
          "charStart": 13490,
          "charEnd": 13493,
          "timeStart": 821,
          "timeEnd": 829
        }
      ]
    },
    "person:strange fire": {
      "id": "person:strange fire",
      "type": "person",
      "canonical": "Strange Fire",
      "aliases": [],
      "mentions": [
        {
          "transcriptId": "AOO5a_jUOzg",
          "charStart": 7122,
          "charEnd": 7134,
          "timeStart": 439,
          "timeEnd": 447
        }
      ]
    },
    "person:mary reese": {
      "id": "person:mary reese",
      "type": "person",
      "canonical": "Mary Reese",
      "aliases": [],
      "mentions": [
        {
          "transcriptId": "AOO5a_jUOzg",
          "charStart": 9128,
          "charEnd": 9138,
          "timeStart": 556,
          "timeEnd": 565
        }
      ]
    },
    "person:larry arnold": {
      "id": "person:larry arnold",
      "type": "person",
      "canonical": "Larry Arnold",
      "aliases": [
        "his"
      ],
      "mentions": [
        {
          "transcriptId": "AOO5a_jUOzg",
          "charStart": 9273,
          "charEnd": 9285,
          "timeStart": 565,
          "timeEnd": 574
        },
        {
          "transcriptId": "AOO5a_jUOzg",
          "charStart": 9402,
          "charEnd": 9405,
          "timeStart": 574,
          "timeEnd": 583
        }
      ]
    },
    "person:brian ford": {
      "id": "person:brian ford",
      "type": "person",
      "canonical": "Brian Ford",
      "aliases": [
        "Brian",
        "Ford",
        "he"
      ],
      "mentions": [
        {
          "transcriptId": "AOO5a_jUOzg",
          "charStart": 10520,
          "charEnd": 10530,
          "timeStart": 646,
          "timeEnd": 653
        },
        {
          "transcriptId": "AOO5a_jUOzg",
          "charStart": 10145,
          "charEnd": 10150,
          "timeStart": 623,
          "timeEnd": 631
        },
        {
          "transcriptId": "AOO5a_jUOzg",
          "charStart": 10153,
          "charEnd": 10157,
          "timeStart": 623,
          "timeEnd": 631
        },
        {
          "transcriptId": "AOO5a_jUOzg",
          "charStart": 10593,
          "charEnd": 10595,
          "timeStart": 653,
          "timeEnd": 662
        }
      ]
    },
    "person:falls on": {
      "id": "person:falls on",
      "type": "person",
      "canonical": "Falls On",
      "aliases": [],
      "mentions": [
        {
          "transcriptId": "AOO5a_jUOzg",
          "charStart": 12419,
          "charEnd": 12427,
          "timeStart": 763,
          "timeEnd": 771
        }
      ]
    },
    "person:don carroll": {
      "id": "person:don carroll",
      "type": "person",
      "canonical": "Don Carroll",
      "aliases": [
        "her",
        "his",
        "he",
        "she"
      ],
      "mentions": [
        {
          "transcriptId": "AOO5a_jUOzg",
          "charStart": 14402,
          "charEnd": 14413,
          "timeStart": 878,
          "timeEnd": 886
        },
        {
          "transcriptId": "AOO5a_jUOzg",
          "charStart": 14588,
          "charEnd": 14599,
          "timeStart": 886,
          "timeEnd": 893
        },
        {
          "transcriptId": "AOO5a_jUOzg",
          "charStart": 14469,
          "charEnd": 14472,
          "timeStart": 878,
          "timeEnd": 886
        },
        {
          "transcriptId": "AOO5a_jUOzg",
          "charStart": 14494,
          "charEnd": 14497,
          "timeStart": 878,
          "timeEnd": 886
        },
        {
          "transcriptId": "AOO5a_jUOzg",
          "charStart": 14528,
          "charEnd": 14530,
          "timeStart": 886,
          "timeEnd": 893
        },
        {
          "transcriptId": "AOO5a_jUOzg",
          "charStart": 14551,
          "charEnd": 14554,
          "timeStart": 886,
          "timeEnd": 893
        },
        {
          "transcriptId": "AOO5a_jUOzg",
          "charStart": 14578,
          "charEnd": 14581,
          "timeStart": 886,
          "timeEnd": 893
        },
        {
          "transcriptId": "AOO5a_jUOzg",
          "charStart": 14658,
          "charEnd": 14661,
          "timeStart": 893,
          "timeEnd": 902
        },
        {
          "transcriptId": "AOO5a_jUOzg",
          "charStart": 14662,
          "charEnd": 14665,
          "timeStart": 893,
          "timeEnd": 902
        }
      ]
    },
    "person:john hamer": {
      "id": "person:john hamer",
      "type": "person",
      "canonical": "John Hamer",
      "aliases": [
        "him",
        "she",
        "her",
        "he",
        "his"
      ],
      "mentions": [
        {
          "transcriptId": "AOO5a_jUOzg",
          "charStart": 16144,
          "charEnd": 16154,
          "timeStart": 981,
          "timeEnd": 988
        },
        {
          "transcriptId": "AOO5a_jUOzg",
          "charStart": 16242,
          "charEnd": 16245,
          "timeStart": 988,
          "timeEnd": 997
        },
        {
          "transcriptId": "AOO5a_jUOzg",
          "charStart": 16350,
          "charEnd": 16353,
          "timeStart": 997,
          "timeEnd": 1005
        },
        {
          "transcriptId": "AOO5a_jUOzg",
          "charStart": 16383,
          "charEnd": 16386,
          "timeStart": 997,
          "timeEnd": 1005
        },
        {
          "transcriptId": "AOO5a_jUOzg",
          "charStart": 16418,
          "charEnd": 16421,
          "timeStart": 997,
          "timeEnd": 1005
        },
        {
          "transcriptId": "AOO5a_jUOzg",
          "charStart": 16514,
          "charEnd": 16517,
          "timeStart": 1005,
          "timeEnd": 1013
        },
        {
          "transcriptId": "AOO5a_jUOzg",
          "charStart": 16671,
          "charEnd": 16674,
          "timeStart": 1013,
          "timeEnd": 1022
        },
        {
          "transcriptId": "AOO5a_jUOzg",
          "charStart": 16738,
          "charEnd": 16741,
          "timeStart": 1013,
          "timeEnd": 1022
        },
        {
          "transcriptId": "AOO5a_jUOzg",
          "charStart": 16756,
          "charEnd": 16758,
          "timeStart": 1022,
          "timeEnd": 1030
        },
        {
          "transcriptId": "AOO5a_jUOzg",
          "charStart": 16800,
          "charEnd": 16803,
          "timeStart": 1022,
          "timeEnd": 1030
        }
      ]
    },
    "person:holmes": {
      "id": "person:holmes",
      "type": "person",
      "canonical": "Holmes",
      "aliases": [
        "Mr Holmes"
      ],
      "mentions": [
        {
          "transcriptId": "AOO5a_jUOzg",
          "charStart": 17032,
          "charEnd": 17041,
          "timeStart": 1030,
          "timeEnd": 1038
        },
        {
          "transcriptId": "AOO5a_jUOzg",
          "charStart": 17032,
          "charEnd": 17041,
          "timeStart": 1030,
          "timeEnd": 1038
        }
      ]
    },
    "person:accidental\nfire": {
      "id": "person:accidental\nfire",
      "type": "person",
      "canonical": "Accidental\nFire",
      "aliases": [],
      "mentions": [
        {
          "transcriptId": "AOO5a_jUOzg",
          "charStart": 17824,
          "charEnd": 17839,
          "timeStart": 1073,
          "timeEnd": 1089
        }
      ]
    },
    "person:edelson scotland": {
      "id": "person:edelson scotland",
      "type": "person",
      "canonical": "Edelson Scotland",
      "aliases": [
        "Scotland"
      ],
      "mentions": [
        {
          "transcriptId": "AOO5a_jUOzg",
          "charStart": 19283,
          "charEnd": 19299,
          "timeStart": 1194,
          "timeEnd": 1208
        },
        {
          "transcriptId": "AOO5a_jUOzg",
          "charStart": 18538,
          "charEnd": 18546,
          "timeStart": 1125,
          "timeEnd": 1132
        },
        {
          "transcriptId": "AOO5a_jUOzg",
          "charStart": 18783,
          "charEnd": 18791,
          "timeStart": 1141,
          "timeEnd": 1148
        }
      ]
    },
    "person:google map": {
      "id": "person:google map",
      "type": "person",
      "canonical": "Google Map",
      "aliases": [],
      "mentions": [
        {
          "transcriptId": "AOO5a_jUOzg",
          "charStart": 19337,
          "charEnd": 19347,
          "timeStart": 1194,
          "timeEnd": 1208
        }
      ]
    },
    "person:surf shop": {
      "id": "person:surf shop",
      "type": "person",
      "canonical": "Surf Shop",
      "aliases": [],
      "mentions": [
        {
          "transcriptId": "AOO5a_jUOzg",
          "charStart": 19386,
          "charEnd": 19395,
          "timeStart": 1208,
          "timeEnd": 1215
        }
      ]
    },
    "person:heckle jr": {
      "id": "person:heckle jr",
      "type": "person",
      "canonical": "Heckle Jr",
      "aliases": [
        "Heckle",
        "his"
      ],
      "mentions": [
        {
          "transcriptId": "AOO5a_jUOzg",
          "charStart": 20385,
          "charEnd": 20394,
          "timeStart": 1272,
          "timeEnd": 1280
        },
        {
          "transcriptId": "AOO5a_jUOzg",
          "charStart": 18977,
          "charEnd": 18983,
          "timeStart": 1154,
          "timeEnd": 1157
        },
        {
          "transcriptId": "AOO5a_jUOzg",
          "charStart": 20406,
          "charEnd": 20409,
          "timeStart": 1272,
          "timeEnd": 1280
        }
      ]
    },
    "person:hackensack new jersey": {
      "id": "person:hackensack new jersey",
      "type": "person",
      "canonical": "Hackensack New Jersey",
      "aliases": [],
      "mentions": [
        {
          "transcriptId": "AOO5a_jUOzg",
          "charStart": 20420,
          "charEnd": 20441,
          "timeStart": 1272,
          "timeEnd": 1280
        }
      ]
    },
    "person:john": {
      "id": "person:john",
      "type": "person",
      "canonical": "John",
      "aliases": [
        "Dr John"
      ],
      "mentions": [
        {
          "transcriptId": "AOO5a_jUOzg",
          "charStart": 4483,
          "charEnd": 4490,
          "timeStart": 276,
          "timeEnd": 284
        }
      ]
    },
    "person:richard": {
      "id": "person:richard",
      "type": "person",
      "canonical": "Richard",
      "aliases": [
        "Dr Richard"
      ],
      "mentions": [
        {
          "transcriptId": "AOO5a_jUOzg",
          "charStart": 6219,
          "charEnd": 6229,
          "timeStart": 384,
          "timeEnd": 392
        }
      ]
    },
    "time:2010": {
      "id": "time:2010",
      "type": "time",
      "canonical": "2010",
      "aliases": [],
      "mentions": [
        {
          "transcriptId": "AOO5a_jUOzg",
          "charStart": 1105,
          "charEnd": 1109,
          "timeStart": 71,
          "timeEnd": 78
        },
        {
          "transcriptId": "AOO5a_jUOzg",
          "charStart": 4906,
          "charEnd": 4910,
          "timeStart": 302,
          "timeEnd": 310
        }
      ]
    },
    "time:1979": {
      "id": "time:1979",
      "type": "time",
      "canonical": "1979",
      "aliases": [],
      "mentions": [
        {
          "transcriptId": "AOO5a_jUOzg",
          "charStart": 2072,
          "charEnd": 2076,
          "timeStart": 125,
          "timeEnd": 133
        }
      ]
    },
    "time:1938": {
      "id": "time:1938",
      "type": "time",
      "canonical": "1938",
      "aliases": [],
      "mentions": [
        {
          "transcriptId": "AOO5a_jUOzg",
          "charStart": 4128,
          "charEnd": 4132,
          "timeStart": 249,
          "timeEnd": 258
        }
      ]
    },
    "time:1966": {
      "id": "time:1966",
      "type": "time",
      "canonical": "1966",
      "aliases": [],
      "mentions": [
        {
          "transcriptId": "AOO5a_jUOzg",
          "charStart": 4537,
          "charEnd": 4541,
          "timeStart": 276,
          "timeEnd": 284
        }
      ]
    },
    "time:2007": {
      "id": "time:2007",
      "type": "time",
      "canonical": "2007",
      "aliases": [],
      "mentions": [
        {
          "transcriptId": "AOO5a_jUOzg",
          "charStart": 4665,
          "charEnd": 4669,
          "timeStart": 284,
          "timeEnd": 292
        },
        {
          "transcriptId": "lPpFFU9EMr8",
          "charStart": 5997,
          "charEnd": 6001,
          "timeStart": 384,
          "timeEnd": 391
        },
        {
          "transcriptId": "lPpFFU9EMr8",
          "charStart": 6755,
          "charEnd": 6759,
          "timeStart": 432,
          "timeEnd": 441
        },
        {
          "transcriptId": "lPpFFU9EMr8",
          "charStart": 11877,
          "charEnd": 11881,
          "timeStart": 729,
          "timeEnd": 739
        }
      ]
    },
    "time:2013": {
      "id": "time:2013",
      "type": "time",
      "canonical": "2013",
      "aliases": [],
      "mentions": [
        {
          "transcriptId": "AOO5a_jUOzg",
          "charStart": 5304,
          "charEnd": 5308,
          "timeStart": 328,
          "timeEnd": 336
        }
      ]
    },
    "time:2015": {
      "id": "time:2015",
      "type": "time",
      "canonical": "2015",
      "aliases": [],
      "mentions": [
        {
          "transcriptId": "AOO5a_jUOzg",
          "charStart": 5751,
          "charEnd": 5755,
          "timeStart": 352,
          "timeEnd": 359
        }
      ]
    },
    "time:2016": {
      "id": "time:2016",
      "type": "time",
      "canonical": "2016",
      "aliases": [],
      "mentions": [
        {
          "transcriptId": "AOO5a_jUOzg",
          "charStart": 5875,
          "charEnd": 5879,
          "timeStart": 359,
          "timeEnd": 367
        },
        {
          "transcriptId": "lPpFFU9EMr8",
          "charStart": 16499,
          "charEnd": 16503,
          "timeStart": 1043,
          "timeEnd": 1051
        }
      ]
    },
    "time:1967": {
      "id": "time:1967",
      "type": "time",
      "canonical": "1967",
      "aliases": [],
      "mentions": [
        {
          "transcriptId": "AOO5a_jUOzg",
          "charStart": 6017,
          "charEnd": 6021,
          "timeStart": 367,
          "timeEnd": 375
        }
      ]
    },
    "time:1951": {
      "id": "time:1951",
      "type": "time",
      "canonical": "1951",
      "aliases": [],
      "mentions": [
        {
          "transcriptId": "AOO5a_jUOzg",
          "charStart": 6214,
          "charEnd": 6218,
          "timeStart": 384,
          "timeEnd": 392
        }
      ]
    },
    "time:1982": {
      "id": "time:1982",
      "type": "time",
      "canonical": "1982",
      "aliases": [],
      "mentions": [
        {
          "transcriptId": "AOO5a_jUOzg",
          "charStart": 14308,
          "charEnd": 14312,
          "timeStart": 870,
          "timeEnd": 878
        }
      ]
    },
    "organization:fbi": {
      "id": "organization:fbi",
      "type": "organization",
      "canonical": "FBI",
      "aliases": [],
      "mentions": [
        {
          "transcriptId": "AOO5a_jUOzg",
          "charStart": 8183,
          "charEnd": 8186,
          "timeStart": 498,
          "timeEnd": 507
        },
        {
          "transcriptId": "AOO5a_jUOzg",
          "charStart": 8204,
          "charEnd": 8207,
          "timeStart": 498,
          "timeEnd": 507
        }
      ]
    },
    "organization:google": {
      "id": "organization:google",
      "type": "organization",
      "canonical": "Google",
      "aliases": [],
      "mentions": [
        {
          "transcriptId": "AOO5a_jUOzg",
          "charStart": 19337,
          "charEnd": 19343,
          "timeStart": 1194,
          "timeEnd": 1208
        }
      ]
    },
    "thing:oil": {
      "id": "thing:oil",
      "type": "thing",
      "canonical": "oil",
      "aliases": [],
      "mentions": [
        {
          "transcriptId": "AOO5a_jUOzg",
          "charStart": 2936,
          "charEnd": 2939,
          "timeStart": 173,
          "timeEnd": 181
        },
        {
          "transcriptId": "AOO5a_jUOzg",
          "charStart": 2944,
          "charEnd": 2947,
          "timeStart": 181,
          "timeEnd": 191
        }
      ]
    },
    "person:dark as": {
      "id": "person:dark as",
      "type": "person",
      "canonical": "Dark As",
      "aliases": [],
      "mentions": [
        {
          "transcriptId": "lPpFFU9EMr8",
          "charStart": 213,
          "charEnd": 220,
          "timeStart": 9,
          "timeEnd": 16
        }
      ]
    },
    "person:northern michigan": {
      "id": "person:northern michigan",
      "type": "person",
      "canonical": "Northern Michigan",
      "aliases": [],
      "mentions": [
        {
          "transcriptId": "lPpFFU9EMr8",
          "charStart": 773,
          "charEnd": 790,
          "timeStart": 48,
          "timeEnd": 57
        },
        {
          "transcriptId": "lPpFFU9EMr8",
          "charStart": 1493,
          "charEnd": 1510,
          "timeStart": 95,
          "timeEnd": 102
        },
        {
          "transcriptId": "lPpFFU9EMr8",
          "charStart": 9010,
          "charEnd": 9027,
          "timeStart": 563,
          "timeEnd": 572
        }
      ]
    },
    "person:steve cook": {
      "id": "person:steve cook",
      "type": "person",
      "canonical": "Steve Cook",
      "aliases": [],
      "mentions": [
        {
          "transcriptId": "lPpFFU9EMr8",
          "charStart": 1245,
          "charEnd": 1255,
          "timeStart": 80,
          "timeEnd": 88
        },
        {
          "transcriptId": "lPpFFU9EMr8",
          "charStart": 20218,
          "charEnd": 20228,
          "timeStart": 1263,
          "timeEnd": 1271
        }
      ]
    },
    "person:april\nfool": {
      "id": "person:april\nfool",
      "type": "person",
      "canonical": "April\nFool",
      "aliases": [],
      "mentions": [
        {
          "transcriptId": "lPpFFU9EMr8",
          "charStart": 1303,
          "charEnd": 1313,
          "timeStart": 80,
          "timeEnd": 95
        }
      ]
    },
    "person:north woods\ndarkness": {
      "id": "person:north woods\ndarkness",
      "type": "person",
      "canonical": "North Woods\nDarkness",
      "aliases": [
        "Darkness"
      ],
      "mentions": [
        {
          "transcriptId": "lPpFFU9EMr8",
          "charStart": 1639,
          "charEnd": 1659,
          "timeStart": 102,
          "timeEnd": 119
        },
        {
          "transcriptId": "lPpFFU9EMr8",
          "charStart": 12658,
          "charEnd": 12666,
          "timeStart": 778,
          "timeEnd": 786
        }
      ]
    },
    "person:native american": {
      "id": "person:native american",
      "type": "person",
      "canonical": "Native American",
      "aliases": [],
      "mentions": [
        {
          "transcriptId": "lPpFFU9EMr8",
          "charStart": 2581,
          "charEnd": 2596,
          "timeStart": 167,
          "timeEnd": 175
        }
      ]
    },
    "person:the watchmen": {
      "id": "person:the watchmen",
      "type": "person",
      "canonical": "The Watchmen",
      "aliases": [
        "Watchmen"
      ],
      "mentions": [
        {
          "transcriptId": "lPpFFU9EMr8",
          "charStart": 3209,
          "charEnd": 3221,
          "timeStart": 207,
          "timeEnd": 214
        },
        {
          "transcriptId": "lPpFFU9EMr8",
          "charStart": 3528,
          "charEnd": 3536,
          "timeStart": 223,
          "timeEnd": 232
        },
        {
          "transcriptId": "lPpFFU9EMr8",
          "charStart": 4158,
          "charEnd": 4166,
          "timeStart": 264,
          "timeEnd": 271
        }
      ]
    },
    "person:the crickets": {
      "id": "person:the crickets",
      "type": "person",
      "canonical": "The Crickets",
      "aliases": [],
      "mentions": [
        {
          "transcriptId": "lPpFFU9EMr8",
          "charStart": 3439,
          "charEnd": 3451,
          "timeStart": 223,
          "timeEnd": 232
        }
      ]
    },
    "person:the watchman": {
      "id": "person:the watchman",
      "type": "person",
      "canonical": "The Watchman",
      "aliases": [
        "Watchman",
        "his",
        "him",
        "he"
      ],
      "mentions": [
        {
          "transcriptId": "lPpFFU9EMr8",
          "charStart": 3744,
          "charEnd": 3756,
          "timeStart": 240,
          "timeEnd": 248
        },
        {
          "transcriptId": "lPpFFU9EMr8",
          "charStart": 2969,
          "charEnd": 2977,
          "timeStart": 199,
          "timeEnd": 207
        },
        {
          "transcriptId": "lPpFFU9EMr8",
          "charStart": 3072,
          "charEnd": 3080,
          "timeStart": 207,
          "timeEnd": 214
        },
        {
          "transcriptId": "lPpFFU9EMr8",
          "charStart": 4066,
          "charEnd": 4074,
          "timeStart": 255,
          "timeEnd": 264
        },
        {
          "transcriptId": "lPpFFU9EMr8",
          "charStart": 4271,
          "charEnd": 4279,
          "timeStart": 271,
          "timeEnd": 280
        },
        {
          "transcriptId": "lPpFFU9EMr8",
          "charStart": 4574,
          "charEnd": 4582,
          "timeStart": 296,
          "timeEnd": 304
        },
        {
          "transcriptId": "lPpFFU9EMr8",
          "charStart": 21282,
          "charEnd": 21290,
          "timeStart": 1331,
          "timeEnd": 1339
        },
        {
          "transcriptId": "lPpFFU9EMr8",
          "charStart": 2990,
          "charEnd": 2993,
          "timeStart": 199,
          "timeEnd": 207
        },
        {
          "transcriptId": "lPpFFU9EMr8",
          "charStart": 3085,
          "charEnd": 3088,
          "timeStart": 207,
          "timeEnd": 214
        },
        {
          "transcriptId": "lPpFFU9EMr8",
          "charStart": 3180,
          "charEnd": 3183,
          "timeStart": 207,
          "timeEnd": 214
        },
        {
          "transcriptId": "lPpFFU9EMr8",
          "charStart": 3762,
          "charEnd": 3765,
          "timeStart": 240,
          "timeEnd": 248
        },
        {
          "transcriptId": "lPpFFU9EMr8",
          "charStart": 3786,
          "charEnd": 3788,
          "timeStart": 240,
          "timeEnd": 248
        },
        {
          "transcriptId": "lPpFFU9EMr8",
          "charStart": 3857,
          "charEnd": 3859,
          "timeStart": 248,
          "timeEnd": 255
        },
        {
          "transcriptId": "lPpFFU9EMr8",
          "charStart": 4093,
          "charEnd": 4096,
          "timeStart": 264,
          "timeEnd": 271
        },
        {
          "transcriptId": "lPpFFU9EMr8",
          "charStart": 4594,
          "charEnd": 4597,
          "timeStart": 296,
          "timeEnd": 304
        },
        {
          "transcriptId": "lPpFFU9EMr8",
          "charStart": 21348,
          "charEnd": 21351,
          "timeStart": 1331,
          "timeEnd": 1339
        }
      ]
    },
    "person:kodak signet": {
      "id": "person:kodak signet",
      "type": "person",
      "canonical": "Kodak Signet",
      "aliases": [],
      "mentions": [
        {
          "transcriptId": "lPpFFU9EMr8",
          "charStart": 4117,
          "charEnd": 4129,
          "timeStart": 264,
          "timeEnd": 271
        }
      ]
    },
    "person:sparta michigan": {
      "id": "person:sparta michigan",
      "type": "person",
      "canonical": "Sparta Michigan",
      "aliases": [
        "Sparta"
      ],
      "mentions": [
        {
          "transcriptId": "lPpFFU9EMr8",
          "charStart": 4722,
          "charEnd": 4737,
          "timeStart": 304,
          "timeEnd": 312
        },
        {
          "transcriptId": "lPpFFU9EMr8",
          "charStart": 4665,
          "charEnd": 4671,
          "timeStart": 296,
          "timeEnd": 304
        },
        {
          "transcriptId": "lPpFFU9EMr8",
          "charStart": 4675,
          "charEnd": 4681,
          "timeStart": 304,
          "timeEnd": 312
        }
      ]
    },
    "person:grand rapids": {
      "id": "person:grand rapids",
      "type": "person",
      "canonical": "Grand Rapids",
      "aliases": [],
      "mentions": [
        {
          "transcriptId": "lPpFFU9EMr8",
          "charStart": 4769,
          "charEnd": 4781,
          "timeStart": 312,
          "timeEnd": 319
        }
      ]
    },
    "person:reed city michigan": {
      "id": "person:reed city michigan",
      "type": "person",
      "canonical": "Reed City Michigan",
      "aliases": [
        "her",
        "she"
      ],
      "mentions": [
        {
          "transcriptId": "lPpFFU9EMr8",
          "charStart": 5279,
          "charEnd": 5297,
          "timeStart": 337,
          "timeEnd": 344
        },
        {
          "transcriptId": "lPpFFU9EMr8",
          "charStart": 5345,
          "charEnd": 5348,
          "timeStart": 344,
          "timeEnd": 353
        },
        {
          "transcriptId": "lPpFFU9EMr8",
          "charStart": 5367,
          "charEnd": 5370,
          "timeStart": 344,
          "timeEnd": 353
        },
        {
          "transcriptId": "lPpFFU9EMr8",
          "charStart": 5449,
          "charEnd": 5452,
          "timeStart": 344,
          "timeEnd": 353
        },
        {
          "transcriptId": "lPpFFU9EMr8",
          "charStart": 5563,
          "charEnd": 5566,
          "timeStart": 353,
          "timeEnd": 359
        }
      ]
    },
    "person:coffee county": {
      "id": "person:coffee county",
      "type": "person",
      "canonical": "Coffee County",
      "aliases": [],
      "mentions": [
        {
          "transcriptId": "lPpFFU9EMr8",
          "charStart": 6090,
          "charEnd": 6103,
          "timeStart": 391,
          "timeEnd": 399
        }
      ]
    },
    "person:traverse city": {
      "id": "person:traverse city",
      "type": "person",
      "canonical": "Traverse City",
      "aliases": [
        "he"
      ],
      "mentions": [
        {
          "transcriptId": "lPpFFU9EMr8",
          "charStart": 6792,
          "charEnd": 6805,
          "timeStart": 432,
          "timeEnd": 441
        },
        {
          "transcriptId": "lPpFFU9EMr8",
          "charStart": 6806,
          "charEnd": 6808,
          "timeStart": 432,
          "timeEnd": 441
        }
      ]
    },
    "person:cinder road": {
      "id": "person:cinder road",
      "type": "person",
      "canonical": "Cinder Road",
      "aliases": [],
      "mentions": [
        {
          "transcriptId": "lPpFFU9EMr8",
          "charStart": 6842,
          "charEnd": 6853,
          "timeStart": 432,
          "timeEnd": 441
        }
      ]
    },
    "person:amarillo zoo": {
      "id": "person:amarillo zoo",
      "type": "person",
      "canonical": "Amarillo Zoo",
      "aliases": [
        "Amarillo"
      ],
      "mentions": [
        {
          "transcriptId": "lPpFFU9EMr8",
          "charStart": 8585,
          "charEnd": 8597,
          "timeStart": 540,
          "timeEnd": 548
        },
        {
          "transcriptId": "lPpFFU9EMr8",
          "charStart": 8761,
          "charEnd": 8769,
          "timeStart": 548,
          "timeEnd": 555
        }
      ]
    },
    "person:michigan dogman": {
      "id": "person:michigan dogman",
      "type": "person",
      "canonical": "Michigan Dogman",
      "aliases": [],
      "mentions": [
        {
          "transcriptId": "lPpFFU9EMr8",
          "charStart": 8804,
          "charEnd": 8819,
          "timeStart": 548,
          "timeEnd": 555
        }
      ]
    },
    "person:the beast": {
      "id": "person:the beast",
      "type": "person",
      "canonical": "The Beast",
      "aliases": [
        "Beast"
      ],
      "mentions": [
        {
          "transcriptId": "lPpFFU9EMr8",
          "charStart": 9159,
          "charEnd": 9168,
          "timeStart": 572,
          "timeEnd": 581
        },
        {
          "transcriptId": "lPpFFU9EMr8",
          "charStart": 9571,
          "charEnd": 9576,
          "timeStart": 597,
          "timeEnd": 604
        },
        {
          "transcriptId": "lPpFFU9EMr8",
          "charStart": 9948,
          "charEnd": 9953,
          "timeStart": 619,
          "timeEnd": 627
        },
        {
          "transcriptId": "lPpFFU9EMr8",
          "charStart": 11695,
          "charEnd": 11700,
          "timeStart": 721,
          "timeEnd": 729
        },
        {
          "transcriptId": "lPpFFU9EMr8",
          "charStart": 14336,
          "charEnd": 14341,
          "timeStart": 892,
          "timeEnd": 899
        },
        {
          "transcriptId": "lPpFFU9EMr8",
          "charStart": 14402,
          "charEnd": 14407,
          "timeStart": 907,
          "timeEnd": 914
        }
      ]
    },
    "person:bray road": {
      "id": "person:bray road",
      "type": "person",
      "canonical": "Bray Road",
      "aliases": [
        "Bray"
      ],
      "mentions": [
        {
          "transcriptId": "lPpFFU9EMr8",
          "charStart": 9172,
          "charEnd": 9181,
          "timeStart": 572,
          "timeEnd": 581
        },
        {
          "transcriptId": "lPpFFU9EMr8",
          "charStart": 11704,
          "charEnd": 11713,
          "timeStart": 721,
          "timeEnd": 729
        },
        {
          "transcriptId": "lPpFFU9EMr8",
          "charStart": 13070,
          "charEnd": 13079,
          "timeStart": 809,
          "timeEnd": 818
        },
        {
          "transcriptId": "lPpFFU9EMr8",
          "charStart": 9843,
          "charEnd": 9847,
          "timeStart": 611,
          "timeEnd": 619
        }
      ]
    },
    "person:walworth county": {
      "id": "person:walworth county",
      "type": "person",
      "canonical": "Walworth County",
      "aliases": [],
      "mentions": [
        {
          "transcriptId": "lPpFFU9EMr8",
          "charStart": 9208,
          "charEnd": 9223,
          "timeStart": 572,
          "timeEnd": 581
        }
      ]
    },
    "person:linda godfrey": {
      "id": "person:linda godfrey",
      "type": "person",
      "canonical": "Linda Godfrey",
      "aliases": [],
      "mentions": [
        {
          "transcriptId": "lPpFFU9EMr8",
          "charStart": 9597,
          "charEnd": 9610,
          "timeStart": 597,
          "timeEnd": 604
        },
        {
          "transcriptId": "lPpFFU9EMr8",
          "charStart": 10181,
          "charEnd": 10194,
          "timeStart": 627,
          "timeEnd": 636
        },
        {
          "transcriptId": "lPpFFU9EMr8",
          "charStart": 11577,
          "charEnd": 11590,
          "timeStart": 714,
          "timeEnd": 721
        },
        {
          "transcriptId": "lPpFFU9EMr8",
          "charStart": 20754,
          "charEnd": 20767,
          "timeStart": 1294,
          "timeEnd": 1302
        }
      ]
    },
    "person:doris gibson": {
      "id": "person:doris gibson",
      "type": "person",
      "canonical": "Doris Gibson",
      "aliases": [],
      "mentions": [
        {
          "transcriptId": "lPpFFU9EMr8",
          "charStart": 9812,
          "charEnd": 9824,
          "timeStart": 611,
          "timeEnd": 619
        }
      ]
    },
    "person:danny\nmorgan": {
      "id": "person:danny\nmorgan",
      "type": "person",
      "canonical": "Danny\nMorgan",
      "aliases": [
        "Morgan"
      ],
      "mentions": [
        {
          "transcriptId": "lPpFFU9EMr8",
          "charStart": 10246,
          "charEnd": 10258,
          "timeStart": 627,
          "timeEnd": 644
        },
        {
          "transcriptId": "lPpFFU9EMr8",
          "charStart": 10348,
          "charEnd": 10354,
          "timeStart": 636,
          "timeEnd": 644
        }
      ]
    },
    "person:elkhorn wisconsin": {
      "id": "person:elkhorn wisconsin",
      "type": "person",
      "canonical": "Elkhorn Wisconsin",
      "aliases": [
        "Elkhorn",
        "Wisconsin"
      ],
      "mentions": [
        {
          "transcriptId": "lPpFFU9EMr8",
          "charStart": 10272,
          "charEnd": 10289,
          "timeStart": 636,
          "timeEnd": 644
        },
        {
          "transcriptId": "lPpFFU9EMr8",
          "charStart": 13003,
          "charEnd": 13020,
          "timeStart": 809,
          "timeEnd": 818
        },
        {
          "transcriptId": "lPpFFU9EMr8",
          "charStart": 10810,
          "charEnd": 10817,
          "timeStart": 660,
          "timeEnd": 668
        },
        {
          "transcriptId": "lPpFFU9EMr8",
          "charStart": 1169,
          "charEnd": 1178,
          "timeStart": 73,
          "timeEnd": 80
        },
        {
          "transcriptId": "lPpFFU9EMr8",
          "charStart": 9031,
          "charEnd": 9040,
          "timeStart": 563,
          "timeEnd": 572
        }
      ]
    },
    "person:the gable": {
      "id": "person:the gable",
      "type": "person",
      "canonical": "The Gable",
      "aliases": [
        "Gable",
        "his"
      ],
      "mentions": [
        {
          "transcriptId": "lPpFFU9EMr8",
          "charStart": 11844,
          "charEnd": 11853,
          "timeStart": 729,
          "timeEnd": 739
        },
        {
          "transcriptId": "lPpFFU9EMr8",
          "charStart": 11833,
          "charEnd": 11838,
          "timeStart": 729,
          "timeEnd": 739
        },
        {
          "transcriptId": "lPpFFU9EMr8",
          "charStart": 12615,
          "charEnd": 12620,
          "timeStart": 778,
          "timeEnd": 786
        },
        {
          "transcriptId": "lPpFFU9EMr8",
          "charStart": 20150,
          "charEnd": 20155,
          "timeStart": 1263,
          "timeEnd": 1271
        },
        {
          "transcriptId": "lPpFFU9EMr8",
          "charStart": 12073,
          "charEnd": 12076,
          "timeStart": 739,
          "timeEnd": 746
        }
      ]
    },
    "person:wolf man": {
      "id": "person:wolf man",
      "type": "person",
      "canonical": "Wolf Man",
      "aliases": [],
      "mentions": [
        {
          "transcriptId": "lPpFFU9EMr8",
          "charStart": 13765,
          "charEnd": 13773,
          "timeStart": 850,
          "timeEnd": 859
        }
      ]
    },
    "person:petrus gonzalez": {
      "id": "person:petrus gonzalez",
      "type": "person",
      "canonical": "Petrus Gonzalez",
      "aliases": [
        "Gonzalez",
        "he",
        "his"
      ],
      "mentions": [
        {
          "transcriptId": "lPpFFU9EMr8",
          "charStart": 13924,
          "charEnd": 13939,
          "timeStart": 867,
          "timeEnd": 876
        },
        {
          "transcriptId": "lPpFFU9EMr8",
          "charStart": 14234,
          "charEnd": 14242,
          "timeStart": 884,
          "timeEnd": 892
        },
        {
          "transcriptId": "lPpFFU9EMr8",
          "charStart": 13940,
          "charEnd": 13942,
          "timeStart": 867,
          "timeEnd": 876
        },
        {
          "transcriptId": "lPpFFU9EMr8",
          "charStart": 14048,
          "charEnd": 14050,
          "timeStart": 876,
          "timeEnd": 884
        },
        {
          "transcriptId": "lPpFFU9EMr8",
          "charStart": 14101,
          "charEnd": 14104,
          "timeStart": 876,
          "timeEnd": 884
        }
      ]
    },
    "person:lady catherine": {
      "id": "person:lady catherine",
      "type": "person",
      "canonical": "Lady Catherine",
      "aliases": [],
      "mentions": [
        {
          "transcriptId": "lPpFFU9EMr8",
          "charStart": 14257,
          "charEnd": 14271,
          "timeStart": 884,
          "timeEnd": 892
        }
      ]
    },
    "person:tale as old as time": {
      "id": "person:tale as old as time",
      "type": "person",
      "canonical": "Tale As Old As Time",
      "aliases": [],
      "mentions": [
        {
          "transcriptId": "lPpFFU9EMr8",
          "charStart": 14344,
          "charEnd": 14363,
          "timeStart": 892,
          "timeEnd": 899
        }
      ]
    },
    "person:rudy eugene": {
      "id": "person:rudy eugene",
      "type": "person",
      "canonical": "Rudy Eugene",
      "aliases": [
        "he",
        "his",
        "him"
      ],
      "mentions": [
        {
          "transcriptId": "lPpFFU9EMr8",
          "charStart": 15261,
          "charEnd": 15272,
          "timeStart": 964,
          "timeEnd": 972
        },
        {
          "transcriptId": "lPpFFU9EMr8",
          "charStart": 15775,
          "charEnd": 15786,
          "timeStart": 995,
          "timeEnd": 1003
        },
        {
          "transcriptId": "lPpFFU9EMr8",
          "charStart": 15326,
          "charEnd": 15328,
          "timeStart": 964,
          "timeEnd": 972
        },
        {
          "transcriptId": "lPpFFU9EMr8",
          "charStart": 15341,
          "charEnd": 15344,
          "timeStart": 972,
          "timeEnd": 979
        },
        {
          "transcriptId": "lPpFFU9EMr8",
          "charStart": 15812,
          "charEnd": 15814,
          "timeStart": 1003,
          "timeEnd": 1010
        },
        {
          "transcriptId": "lPpFFU9EMr8",
          "charStart": 15858,
          "charEnd": 15861,
          "timeStart": 1003,
          "timeEnd": 1010
        },
        {
          "transcriptId": "lPpFFU9EMr8",
          "charStart": 15877,
          "charEnd": 15879,
          "timeStart": 1003,
          "timeEnd": 1010
        }
      ]
    },
    "person:ronald papo eugene": {
      "id": "person:ronald papo eugene",
      "type": "person",
      "canonical": "Ronald Papo Eugene",
      "aliases": [
        "Ronald",
        "Papo",
        "he"
      ],
      "mentions": [
        {
          "transcriptId": "lPpFFU9EMr8",
          "charStart": 15382,
          "charEnd": 15400,
          "timeStart": 972,
          "timeEnd": 979
        },
        {
          "transcriptId": "lPpFFU9EMr8",
          "charStart": 15942,
          "charEnd": 15948,
          "timeStart": 1010,
          "timeEnd": 1018
        },
        {
          "transcriptId": "lPpFFU9EMr8",
          "charStart": 15450,
          "charEnd": 15454,
          "timeStart": 979,
          "timeEnd": 988
        },
        {
          "transcriptId": "lPpFFU9EMr8",
          "charStart": 16076,
          "charEnd": 16078,
          "timeStart": 1018,
          "timeEnd": 1026
        }
      ]
    },
    "person:trace amounts": {
      "id": "person:trace amounts",
      "type": "person",
      "canonical": "Trace Amounts",
      "aliases": [
        "his",
        "him",
        "he"
      ],
      "mentions": [
        {
          "transcriptId": "lPpFFU9EMr8",
          "charStart": 16246,
          "charEnd": 16259,
          "timeStart": 1026,
          "timeEnd": 1034
        },
        {
          "transcriptId": "lPpFFU9EMr8",
          "charStart": 16344,
          "charEnd": 16347,
          "timeStart": 1034,
          "timeEnd": 1043
        },
        {
          "transcriptId": "lPpFFU9EMr8",
          "charStart": 16528,
          "charEnd": 16531,
          "timeStart": 1043,
          "timeEnd": 1051
        },
        {
          "transcriptId": "lPpFFU9EMr8",
          "charStart": 16532,
          "charEnd": 16534,
          "timeStart": 1043,
          "timeEnd": 1051
        },
        {
          "transcriptId": "lPpFFU9EMr8",
          "charStart": 16572,
          "charEnd": 16574,
          "timeStart": 1051,
          "timeEnd": 1059
        },
        {
          "transcriptId": "lPpFFU9EMr8",
          "charStart": 16581,
          "charEnd": 16584,
          "timeStart": 1051,
          "timeEnd": 1059
        },
        {
          "transcriptId": "lPpFFU9EMr8",
          "charStart": 16613,
          "charEnd": 16615,
          "timeStart": 1051,
          "timeEnd": 1059
        },
        {
          "transcriptId": "lPpFFU9EMr8",
          "charStart": 16653,
          "charEnd": 16655,
          "timeStart": 1051,
          "timeEnd": 1059
        },
        {
          "transcriptId": "lPpFFU9EMr8",
          "charStart": 16726,
          "charEnd": 16729,
          "timeStart": 1059,
          "timeEnd": 1067
        },
        {
          "transcriptId": "lPpFFU9EMr8",
          "charStart": 16799,
          "charEnd": 16801,
          "timeStart": 1059,
          "timeEnd": 1067
        },
        {
          "transcriptId": "lPpFFU9EMr8",
          "charStart": 16925,
          "charEnd": 16927,
          "timeStart": 1067,
          "timeEnd": 1074
        },
        {
          "transcriptId": "lPpFFU9EMr8",
          "charStart": 16976,
          "charEnd": 16979,
          "timeStart": 1074,
          "timeEnd": 1082
        }
      ]
    },
    "person:august austin": {
      "id": "person:august austin",
      "type": "person",
      "canonical": "August Austin",
      "aliases": [],
      "mentions": [
        {
          "transcriptId": "lPpFFU9EMr8",
          "charStart": 17008,
          "charEnd": 17021,
          "timeStart": 1074,
          "timeEnd": 1082
        }
      ]
    },
    "person:john stevens": {
      "id": "person:john stevens",
      "type": "person",
      "canonical": "John Stevens",
      "aliases": [
        "his"
      ],
      "mentions": [
        {
          "transcriptId": "lPpFFU9EMr8",
          "charStart": 17384,
          "charEnd": 17396,
          "timeStart": 1098,
          "timeEnd": 1106
        },
        {
          "transcriptId": "lPpFFU9EMr8",
          "charStart": 17401,
          "charEnd": 17404,
          "timeStart": 1098,
          "timeEnd": 1106
        }
      ]
    },
    "person:michelle michonne michelle": {
      "id": "person:michelle michonne michelle",
      "type": "person",
      "canonical": "Michelle Michonne Michelle",
      "aliases": [],
      "mentions": [
        {
          "transcriptId": "lPpFFU9EMr8",
          "charStart": 17410,
          "charEnd": 17436,
          "timeStart": 1098,
          "timeEnd": 1106
        }
      ]
    },
    "person:jeffrey fisher": {
      "id": "person:jeffrey fisher",
      "type": "person",
      "canonical": "Jeffrey Fisher",
      "aliases": [],
      "mentions": [
        {
          "transcriptId": "lPpFFU9EMr8",
          "charStart": 17561,
          "charEnd": 17575,
          "timeStart": 1106,
          "timeEnd": 1113
        }
      ]
    },
    "person:michelle jeff": {
      "id": "person:michelle jeff",
      "type": "person",
      "canonical": "Michelle Jeff",
      "aliases": [
        "Jeff",
        "her",
        "him",
        "his",
        "he"
      ],
      "mentions": [
        {
          "transcriptId": "lPpFFU9EMr8",
          "charStart": 17666,
          "charEnd": 17679,
          "timeStart": 1113,
          "timeEnd": 1122
        },
        {
          "transcriptId": "lPpFFU9EMr8",
          "charStart": 17790,
          "charEnd": 17794,
          "timeStart": 1122,
          "timeEnd": 1129
        },
        {
          "transcriptId": "lPpFFU9EMr8",
          "charStart": 17883,
          "charEnd": 17887,
          "timeStart": 1122,
          "timeEnd": 1129
        },
        {
          "transcriptId": "lPpFFU9EMr8",
          "charStart": 18024,
          "charEnd": 18028,
          "timeStart": 1137,
          "timeEnd": 1145
        },
        {
          "transcriptId": "lPpFFU9EMr8",
          "charStart": 18152,
          "charEnd": 18156,
          "timeStart": 1137,
          "timeEnd": 1145
        },
        {
          "transcriptId": "lPpFFU9EMr8",
          "charStart": 18206,
          "charEnd": 18210,
          "timeStart": 1145,
          "timeEnd": 1154
        },
        {
          "transcriptId": "lPpFFU9EMr8",
          "charStart": 17777,
          "charEnd": 17780,
          "timeStart": 1122,
          "timeEnd": 1129
        },
        {
          "transcriptId": "lPpFFU9EMr8",
          "charStart": 17815,
          "charEnd": 17818,
          "timeStart": 1122,
          "timeEnd": 1129
        },
        {
          "transcriptId": "lPpFFU9EMr8",
          "charStart": 17901,
          "charEnd": 17904,
          "timeStart": 1129,
          "timeEnd": 1137
        },
        {
          "transcriptId": "lPpFFU9EMr8",
          "charStart": 17912,
          "charEnd": 17914,
          "timeStart": 1129,
          "timeEnd": 1137
        },
        {
          "transcriptId": "lPpFFU9EMr8",
          "charStart": 17963,
          "charEnd": 17966,
          "timeStart": 1129,
          "timeEnd": 1137
        },
        {
          "transcriptId": "lPpFFU9EMr8",
          "charStart": 18046,
          "charEnd": 18049,
          "timeStart": 1137,
          "timeEnd": 1145
        },
        {
          "transcriptId": "lPpFFU9EMr8",
          "charStart": 18132,
          "charEnd": 18135,
          "timeStart": 1137,
          "timeEnd": 1145
        },
        {
          "transcriptId": "lPpFFU9EMr8",
          "charStart": 18178,
          "charEnd": 18181,
          "timeStart": 1145,
          "timeEnd": 1154
        },
        {
          "transcriptId": "lPpFFU9EMr8",
          "charStart": 18247,
          "charEnd": 18249,
          "timeStart": 1145,
          "timeEnd": 1154
        },
        {
          "transcriptId": "lPpFFU9EMr8",
          "charStart": 18379,
          "charEnd": 18382,
          "timeStart": 1154,
          "timeEnd": 1161
        }
      ]
    },
    "person:john\njohn": {
      "id": "person:john\njohn",
      "type": "person",
      "canonical": "John\nJohn",
      "aliases": [],
      "mentions": [
        {
          "transcriptId": "lPpFFU9EMr8",
          "charStart": 18428,
          "charEnd": 18437,
          "timeStart": 1154,
          "timeEnd": 1168
        }
      ]
    },
    "person:austin john": {
      "id": "person:austin john",
      "type": "person",
      "canonical": "Austin John",
      "aliases": [
        "his"
      ],
      "mentions": [
        {
          "transcriptId": "lPpFFU9EMr8",
          "charStart": 19275,
          "charEnd": 19286,
          "timeStart": 1203,
          "timeEnd": 1210
        },
        {
          "transcriptId": "lPpFFU9EMr8",
          "charStart": 19437,
          "charEnd": 19440,
          "timeStart": 1210,
          "timeEnd": 1219
        },
        {
          "transcriptId": "lPpFFU9EMr8",
          "charStart": 19519,
          "charEnd": 19522,
          "timeStart": 1219,
          "timeEnd": 1226
        }
      ]
    },
    "person:philip resnick": {
      "id": "person:philip resnick",
      "type": "person",
      "canonical": "Philip Resnick",
      "aliases": [
        "Resnick",
        "his",
        "he"
      ],
      "mentions": [
        {
          "transcriptId": "lPpFFU9EMr8",
          "charStart": 19606,
          "charEnd": 19620,
          "timeStart": 1226,
          "timeEnd": 1233
        },
        {
          "transcriptId": "lPpFFU9EMr8",
          "charStart": 19705,
          "charEnd": 19712,
          "timeStart": 1233,
          "timeEnd": 1241
        },
        {
          "transcriptId": "lPpFFU9EMr8",
          "charStart": 19686,
          "charEnd": 19689,
          "timeStart": 1233,
          "timeEnd": 1241
        },
        {
          "transcriptId": "lPpFFU9EMr8",
          "charStart": 19784,
          "charEnd": 19786,
          "timeStart": 1233,
          "timeEnd": 1241
        },
        {
          "transcriptId": "lPpFFU9EMr8",
          "charStart": 19795,
          "charEnd": 19797,
          "timeStart": 1241,
          "timeEnd": 1249
        }
      ]
    },
    "person:the\nlegend": {
      "id": "person:the\nlegend",
      "type": "person",
      "canonical": "The\nLegend",
      "aliases": [
        "Legend",
        "he"
      ],
      "mentions": [
        {
          "transcriptId": "lPpFFU9EMr8",
          "charStart": 20236,
          "charEnd": 20246,
          "timeStart": 1263,
          "timeEnd": 1279
        },
        {
          "transcriptId": "lPpFFU9EMr8",
          "charStart": 8348,
          "charEnd": 8354,
          "timeStart": 519,
          "timeEnd": 526
        },
        {
          "transcriptId": "lPpFFU9EMr8",
          "charStart": 9089,
          "charEnd": 9095,
          "timeStart": 563,
          "timeEnd": 572
        },
        {
          "transcriptId": "lPpFFU9EMr8",
          "charStart": 10161,
          "charEnd": 10167,
          "timeStart": 627,
          "timeEnd": 636
        },
        {
          "transcriptId": "lPpFFU9EMr8",
          "charStart": 8430,
          "charEnd": 8432,
          "timeStart": 526,
          "timeEnd": 530
        },
        {
          "transcriptId": "lPpFFU9EMr8",
          "charStart": 8464,
          "charEnd": 8466,
          "timeStart": 526,
          "timeEnd": 530
        }
      ]
    },
    "time:1987": {
      "id": "time:1987",
      "type": "time",
      "canonical": "1987",
      "aliases": [],
      "mentions": [
        {
          "transcriptId": "lPpFFU9EMr8",
          "charStart": 1221,
          "charEnd": 1225,
          "timeStart": 80,
          "timeEnd": 88
        },
        {
          "transcriptId": "lPpFFU9EMr8",
          "charStart": 4657,
          "charEnd": 4661,
          "timeStart": 296,
          "timeEnd": 304
        },
        {
          "transcriptId": "lPpFFU9EMr8",
          "charStart": 4738,
          "charEnd": 4742,
          "timeStart": 304,
          "timeEnd": 312
        }
      ]
    },
    "time:1961": {
      "id": "time:1961",
      "type": "time",
      "canonical": "1961",
      "aliases": [],
      "mentions": [
        {
          "transcriptId": "lPpFFU9EMr8",
          "charStart": 2956,
          "charEnd": 2960,
          "timeStart": 199,
          "timeEnd": 207
        }
      ]
    },
    "time:1993": {
      "id": "time:1993",
      "type": "time",
      "canonical": "1993",
      "aliases": [],
      "mentions": [
        {
          "transcriptId": "lPpFFU9EMr8",
          "charStart": 5298,
          "charEnd": 5302,
          "timeStart": 337,
          "timeEnd": 344
        }
      ]
    },
    "time:1994": {
      "id": "time:1994",
      "type": "time",
      "canonical": "1994",
      "aliases": [],
      "mentions": [
        {
          "transcriptId": "lPpFFU9EMr8",
          "charStart": 5760,
          "charEnd": 5764,
          "timeStart": 368,
          "timeEnd": 376
        }
      ]
    },
    "time:2001": {
      "id": "time:2001",
      "type": "time",
      "canonical": "2001",
      "aliases": [],
      "mentions": [
        {
          "transcriptId": "lPpFFU9EMr8",
          "charStart": 5779,
          "charEnd": 5783,
          "timeStart": 368,
          "timeEnd": 376
        }
      ]
    },
    "time:2018": {
      "id": "time:2018",
      "type": "time",
      "canonical": "2018",
      "aliases": [],
      "mentions": [
        {
          "transcriptId": "lPpFFU9EMr8",
          "charStart": 10210,
          "charEnd": 10214,
          "timeStart": 627,
          "timeEnd": 636
        }
      ]
    },
    "time:2020": {
      "id": "time:2020",
      "type": "time",
      "canonical": "2020",
      "aliases": [],
      "mentions": [
        {
          "transcriptId": "lPpFFU9EMr8",
          "charStart": 10733,
          "charEnd": 10737,
          "timeStart": 660,
          "timeEnd": 668
        }
      ]
    },
    "time:2012": {
      "id": "time:2012",
      "type": "time",
      "canonical": "2012",
      "aliases": [],
      "mentions": [
        {
          "transcriptId": "lPpFFU9EMr8",
          "charStart": 15256,
          "charEnd": 15260,
          "timeStart": 964,
          "timeEnd": 972
        }
      ]
    },
    "time:1959": {
      "id": "time:1959",
      "type": "time",
      "canonical": "1959",
      "aliases": [],
      "mentions": [
        {
          "transcriptId": "TSZ9wPPcszo",
          "charStart": 79,
          "charEnd": 83,
          "timeStart": 3,
          "timeEnd": 10
        },
        {
          "transcriptId": "TSZ9wPPcszo",
          "charStart": 1116,
          "charEnd": 1120,
          "timeStart": 75,
          "timeEnd": 84
        }
      ]
    },
    "time:1957": {
      "id": "time:1957",
      "type": "time",
      "canonical": "1957",
      "aliases": [],
      "mentions": [
        {
          "transcriptId": "TSZ9wPPcszo",
          "charStart": 10097,
          "charEnd": 10101,
          "timeStart": 612,
          "timeEnd": 621
        }
      ]
    },
    "time:2014": {
      "id": "time:2014",
      "type": "time",
      "canonical": "2014",
      "aliases": [],
      "mentions": [
        {
          "transcriptId": "TSZ9wPPcszo",
          "charStart": 10665,
          "charEnd": 10669,
          "timeStart": 651,
          "timeEnd": 659
        }
      ]
    },
    "time:1990": {
      "id": "time:1990",
      "type": "time",
      "canonical": "1990",
      "aliases": [],
      "mentions": [
        {
          "transcriptId": "TSZ9wPPcszo",
          "charStart": 12019,
          "charEnd": 12023,
          "timeStart": 724,
          "timeEnd": 733
        }
      ]
    },
    "organization:cia": {
      "id": "organization:cia",
      "type": "organization",
      "canonical": "CIA",
      "aliases": [
        "cia"
      ],
      "mentions": [
        {
          "transcriptId": "TSZ9wPPcszo",
          "charStart": 9352,
          "charEnd": 9355,
          "timeStart": 556,
          "timeEnd": 564
        },
        {
          "transcriptId": "TSZ9wPPcszo",
          "charStart": 9635,
          "charEnd": 9638,
          "timeStart": 581,
          "timeEnd": 588
        },
        {
          "transcriptId": "TSZ9wPPcszo",
          "charStart": 10378,
          "charEnd": 10381,
          "timeStart": 621,
          "timeEnd": 629
        },
        {
          "transcriptId": "2NMBjRd8PXw",
          "charStart": 614,
          "charEnd": 617,
          "timeStart": 30.72,
          "timeEnd": 36.32
        }
      ]
    },
    "location:moscow": {
      "id": "location:moscow",
      "type": "location",
      "canonical": "Moscow",
      "aliases": [
        "moscow"
      ],
      "mentions": [
        {
          "transcriptId": "TSZ9wPPcszo",
          "charStart": 9939,
          "charEnd": 9945,
          "timeStart": 596,
          "timeEnd": 603
        }
      ]
    },
    "event:cold war": {
      "id": "event:cold war",
      "type": "event",
      "canonical": "Cold War",
      "aliases": [
        "cold war"
      ],
      "mentions": [
        {
          "transcriptId": "TSZ9wPPcszo",
          "charStart": 9378,
          "charEnd": 9386,
          "timeStart": 564,
          "timeEnd": 573
        }
      ]
    },
    "time:2011": {
      "id": "time:2011",
      "type": "time",
      "canonical": "2011",
      "aliases": [],
      "mentions": [
        {
          "transcriptId": "bAUN1GJD5BQ",
          "charStart": 3,
          "charEnd": 7,
          "timeStart": 1,
          "timeEnd": 9
        }
      ]
    },
    "time:1905": {
      "id": "time:1905",
      "type": "time",
      "canonical": "1905",
      "aliases": [],
      "mentions": [
        {
          "transcriptId": "bAUN1GJD5BQ",
          "charStart": 2098,
          "charEnd": 2102,
          "timeStart": 119,
          "timeEnd": 127
        }
      ]
    },
    "time:1977": {
      "id": "time:1977",
      "type": "time",
      "canonical": "1977",
      "aliases": [],
      "mentions": [
        {
          "transcriptId": "bAUN1GJD5BQ",
          "charStart": 3771,
          "charEnd": 3775,
          "timeStart": 238,
          "timeEnd": 245
        }
      ]
    },
    "time:1981": {
      "id": "time:1981",
      "type": "time",
      "canonical": "1981",
      "aliases": [],
      "mentions": [
        {
          "transcriptId": "bAUN1GJD5BQ",
          "charStart": 3912,
          "charEnd": 3916,
          "timeStart": 245,
          "timeEnd": 253
        }
      ]
    },
    "time:1939": {
      "id": "time:1939",
      "type": "time",
      "canonical": "1939",
      "aliases": [],
      "mentions": [
        {
          "transcriptId": "bAUN1GJD5BQ",
          "charStart": 4017,
          "charEnd": 4021,
          "timeStart": 253,
          "timeEnd": 262
        }
      ]
    },
    "person:the kennedy": {
      "id": "person:the kennedy",
      "type": "person",
      "canonical": "The Kennedy",
      "aliases": [],
      "mentions": [
        {
          "transcriptId": "2NMBjRd8PXw",
          "charStart": 0,
          "charEnd": 11,
          "timeStart": 0,
          "timeEnd": 3.68
        }
      ]
    },
    "person:peter levenda": {
      "id": "person:peter levenda",
      "type": "person",
      "canonical": "Peter Levenda",
      "aliases": [
        "he",
        "his"
      ],
      "mentions": [
        {
          "transcriptId": "2NMBjRd8PXw",
          "charStart": 314,
          "charEnd": 327,
          "timeStart": 13.92,
          "timeEnd": 18.12
        },
        {
          "transcriptId": "2NMBjRd8PXw",
          "charStart": 334,
          "charEnd": 336,
          "timeStart": 13.92,
          "timeEnd": 18.12
        },
        {
          "transcriptId": "2NMBjRd8PXw",
          "charStart": 345,
          "charEnd": 347,
          "timeStart": 15.6,
          "timeEnd": 20.28
        },
        {
          "transcriptId": "2NMBjRd8PXw",
          "charStart": 387,
          "charEnd": 390,
          "timeStart": 18.12,
          "timeEnd": 22.32
        }
      ]
    },
    "person:secret service": {
      "id": "person:secret service",
      "type": "person",
      "canonical": "Secret Service",
      "aliases": [],
      "mentions": [
        {
          "transcriptId": "2NMBjRd8PXw",
          "charStart": 404,
          "charEnd": 418,
          "timeStart": 18.12,
          "timeEnd": 22.32
        }
      ]
    },
    "person:bobby kennedy": {
      "id": "person:bobby kennedy",
      "type": "person",
      "canonical": "Bobby Kennedy",
      "aliases": [
        "him"
      ],
      "mentions": [
        {
          "transcriptId": "2NMBjRd8PXw",
          "charStart": 433,
          "charEnd": 446,
          "timeStart": 20.28,
          "timeEnd": 23.92
        },
        {
          "transcriptId": "2NMBjRd8PXw",
          "charStart": 1395,
          "charEnd": 1408,
          "timeStart": 72.28,
          "timeEnd": 77.76
        },
        {
          "transcriptId": "2NMBjRd8PXw",
          "charStart": 473,
          "charEnd": 476,
          "timeStart": 22.32,
          "timeEnd": 26.36
        }
      ]
    },
    "person:iron\ncurtain": {
      "id": "person:iron\ncurtain",
      "type": "person",
      "canonical": "Iron\nCurtain",
      "aliases": [],
      "mentions": [
        {
          "transcriptId": "2NMBjRd8PXw",
          "charStart": 1165,
          "charEnd": 1177,
          "timeStart": 61.24,
          "timeEnd": 65.519
        }
      ]
    },
    "person:slovak orthodox": {
      "id": "person:slovak orthodox",
      "type": "person",
      "canonical": "Slovak Orthodox",
      "aliases": [],
      "mentions": [
        {
          "transcriptId": "2NMBjRd8PXw",
          "charStart": 1207,
          "charEnd": 1222,
          "timeStart": 63.36,
          "timeEnd": 66.8
        }
      ]
    },
    "person:united states": {
      "id": "person:united states",
      "type": "person",
      "canonical": "United States",
      "aliases": [],
      "mentions": [
        {
          "transcriptId": "2NMBjRd8PXw",
          "charStart": 1904,
          "charEnd": 1917,
          "timeStart": 101.28,
          "timeEnd": 103.84
        }
      ]
    },
    "person:colonia dignidad": {
      "id": "person:colonia dignidad",
      "type": "person",
      "canonical": "Colonia Dignidad",
      "aliases": [],
      "mentions": [
        {
          "transcriptId": "2NMBjRd8PXw",
          "charStart": 2150,
          "charEnd": 2166,
          "timeStart": 113.12,
          "timeEnd": 116.68
        }
      ]
    }
  },
  "relationships": {
    "time:2010|located-at|person:galway ireland|AOO5a_jUOzg:1105-1127": {
      "id": "time:2010|located-at|person:galway ireland|AOO5a_jUOzg:1105-1127",
      "subjectId": "time:2010",
      "predicate": "located-at",
      "objectId": "person:galway ireland",
      "evidence": {
        "transcriptId": "AOO5a_jUOzg",
        "charStart": 1105,
        "charEnd": 1127,
        "timeStart": 71,
        "timeEnd": 78
      },
      "confidence": 0.9,
      "provenance": "nlp"
    },
    "time:2010|located-at|person:michael faraday|AOO5a_jUOzg:1105-1155": {
      "id": "time:2010|located-at|person:michael faraday|AOO5a_jUOzg:1105-1155",
      "subjectId": "time:2010",
      "predicate": "located-at",
      "objectId": "person:michael faraday",
      "evidence": {
        "transcriptId": "AOO5a_jUOzg",
        "charStart": 1105,
        "charEnd": 1155,
        "timeStart": 71,
        "timeEnd": 78
      },
      "confidence": 0.6125,
      "provenance": "nlp"
    },
    "time:1979|said|person:frank frank|AOO5a_jUOzg:2072-2126": {
      "id": "time:1979|said|person:frank frank|AOO5a_jUOzg:2072-2126",
      "subjectId": "time:1979",
      "predicate": "said",
      "objectId": "person:frank frank",
      "evidence": {
        "transcriptId": "AOO5a_jUOzg",
        "charStart": 2072,
        "charEnd": 2126,
        "timeStart": 125,
        "timeEnd": 133
      },
      "confidence": 0.5125,
      "provenance": "nlp"
    },
    "person:phyllis newcomb|located-at|person:shire hall|AOO5a_jUOzg:4159-4208": {
      "id": "person:phyllis newcomb|located-at|person:shire hall|AOO5a_jUOzg:4159-4208",
      "subjectId": "person:phyllis newcomb",
      "predicate": "located-at",
      "objectId": "person:shire hall",
      "evidence": {
        "transcriptId": "AOO5a_jUOzg",
        "charStart": 4159,
        "charEnd": 4208,
        "timeStart": 258,
        "timeEnd": 267
      },
      "confidence": 0.7,
      "provenance": "nlp"
    },
    "person:john irving bentley|located-at|time:1966|AOO5a_jUOzg:4483-4541": {
      "id": "person:john irving bentley|located-at|time:1966|AOO5a_jUOzg:4483-4541",
      "subjectId": "person:john irving bentley",
      "predicate": "located-at",
      "objectId": "time:1966",
      "evidence": {
        "transcriptId": "AOO5a_jUOzg",
        "charStart": 4483,
        "charEnd": 4541,
        "timeStart": 276,
        "timeEnd": 284
      },
      "confidence": 0.6,
      "provenance": "nlp"
    },
    "person:john|located-at|time:1966|AOO5a_jUOzg:4483-4541": {
      "id": "person:john|located-at|time:1966|AOO5a_jUOzg:4483-4541",
      "subjectId": "person:john",
      "predicate": "located-at",
      "objectId": "time:1966",
      "evidence": {
        "transcriptId": "AOO5a_jUOzg",
        "charStart": 4483,
        "charEnd": 4541,
        "timeStart": 276,
        "timeEnd": 284
      },
      "confidence": 0.4125,
      "provenance": "nlp"
    },
    "time:2010|located-at|person:galway ireland|AOO5a_jUOzg:4906-4968": {
      "id": "time:2010|located-at|person:galway ireland|AOO5a_jUOzg:4906-4968",
      "subjectId": "time:2010",
      "predicate": "located-at",
      "objectId": "person:galway ireland",
      "evidence": {
        "transcriptId": "AOO5a_jUOzg",
        "charStart": 4906,
        "charEnd": 4968,
        "timeStart": 302,
        "timeEnd": 310
      },
      "confidence": 0.3125,
      "provenance": "nlp"
    },
    "time:2010|located-at|person:galway ireland|AOO5a_jUOzg:4906-4991": {
      "id": "time:2010|located-at|person:galway ireland|AOO5a_jUOzg:4906-4991",
      "subjectId": "time:2010",
      "predicate": "located-at",
      "objectId": "person:galway ireland",
      "evidence": {
        "transcriptId": "AOO5a_jUOzg",
        "charStart": 4906,
        "charEnd": 4991,
        "timeStart": 302,
        "timeEnd": 310
      },
      "confidence": 0.2,
      "provenance": "nlp"
    },
    "person:heckle jr|located-at|person:hackensack new jersey|AOO5a_jUOzg:20385-20441": {
      "id": "person:heckle jr|located-at|person:hackensack new jersey|AOO5a_jUOzg:20385-20441",
      "subjectId": "person:heckle jr",
      "predicate": "located-at",
      "objectId": "person:hackensack new jersey",
      "evidence": {
        "transcriptId": "AOO5a_jUOzg",
        "charStart": 20385,
        "charEnd": 20441,
        "timeStart": 1272,
        "timeEnd": 1280
      },
      "confidence": 0.675,
      "provenance": "nlp"
    },
    "person:heckle jr|located-at|person:hackensack new jersey|AOO5a_jUOzg:20406-20441": {
      "id": "person:heckle jr|located-at|person:hackensack new jersey|AOO5a_jUOzg:20406-20441",
      "subjectId": "person:heckle jr",
      "predicate": "located-at",
      "objectId": "person:hackensack new jersey",
      "evidence": {
        "transcriptId": "AOO5a_jUOzg",
        "charStart": 20406,
        "charEnd": 20441,
        "timeStart": 1272,
        "timeEnd": 1280
      },
      "confidence": 0.8625,
      "provenance": "nlp"
    },
    "person:the watchman|located-at|time:1987|lPpFFU9EMr8:4574-4661": {
      "id": "person:the watchman|located-at|time:1987|lPpFFU9EMr8:4574-4661",
      "subjectId": "person:the watchman",
      "predicate": "located-at",
      "objectId": "time:1987",
      "evidence": {
        "transcriptId": "lPpFFU9EMr8",
        "charStart": 4574,
        "charEnd": 4661,
        "timeStart": 296,
        "timeEnd": 304
      },
      "confidence": 0.2,
      "provenance": "nlp"
    },
    "person:the watchman|located-at|time:1987|lPpFFU9EMr8:4594-4661": {
      "id": "person:the watchman|located-at|time:1987|lPpFFU9EMr8:4594-4661",
      "subjectId": "person:the watchman",
      "predicate": "located-at",
      "objectId": "time:1987",
      "evidence": {
        "transcriptId": "lPpFFU9EMr8",
        "charStart": 4594,
        "charEnd": 4661,
        "timeStart": 296,
        "timeEnd": 304
      },
      "confidence": 0.25,
      "provenance": "nlp"
    },
    "person:the watchman|located-at|person:sparta michigan|lPpFFU9EMr8:4594-4671": {
      "id": "person:the watchman|located-at|person:sparta michigan|lPpFFU9EMr8:4594-4671",
      "subjectId": "person:the watchman",
      "predicate": "located-at",
      "objectId": "person:sparta michigan",
      "evidence": {
        "transcriptId": "lPpFFU9EMr8",
        "charStart": 4594,
        "charEnd": 4671,
        "timeStart": 296,
        "timeEnd": 304
      },
      "confidence": 0.2,
      "provenance": "nlp"
    },
    "time:1987|located-at|person:sparta michigan|lPpFFU9EMr8:4657-4671": {
      "id": "time:1987|located-at|person:sparta michigan|lPpFFU9EMr8:4657-4671",
      "subjectId": "time:1987",
      "predicate": "located-at",
      "objectId": "person:sparta michigan",
      "evidence": {
        "transcriptId": "lPpFFU9EMr8",
        "charStart": 4657,
        "charEnd": 4671,
        "timeStart": 296,
        "timeEnd": 304
      },
      "confidence": 0.9,
      "provenance": "nlp"
    },
    "time:1994|located-at|time:2001|lPpFFU9EMr8:5760-5783": {
      "id": "time:1994|located-at|time:2001|lPpFFU9EMr8:5760-5783",
      "subjectId": "time:1994",
      "predicate": "located-at",
      "objectId": "time:2001",
      "evidence": {
        "transcriptId": "lPpFFU9EMr8",
        "charStart": 5760,
        "charEnd": 5783,
        "timeStart": 368,
        "timeEnd": 376
      },
      "confidence": 0.8125,
      "provenance": "nlp"
    },
    "person:the beast|located-at|person:walworth county|lPpFFU9EMr8:9159-9223": {
      "id": "person:the beast|located-at|person:walworth county|lPpFFU9EMr8:9159-9223",
      "subjectId": "person:the beast",
      "predicate": "located-at",
      "objectId": "person:walworth county",
      "evidence": {
        "transcriptId": "lPpFFU9EMr8",
        "charStart": 9159,
        "charEnd": 9223,
        "timeStart": 572,
        "timeEnd": 581
      },
      "confidence": 0.5,
      "provenance": "nlp"
    },
    "person:bray road|located-at|person:walworth county|lPpFFU9EMr8:9172-9223": {
      "id": "person:bray road|located-at|person:walworth county|lPpFFU9EMr8:9172-9223",
      "subjectId": "person:bray road",
      "predicate": "located-at",
      "objectId": "person:walworth county",
      "evidence": {
        "transcriptId": "lPpFFU9EMr8",
        "charStart": 9172,
        "charEnd": 9223,
        "timeStart": 572,
        "timeEnd": 581
      },
      "confidence": 0.6625,
      "provenance": "nlp"
    },
    "person:the\nlegend|located-at|time:2018|lPpFFU9EMr8:10161-10214": {
      "id": "person:the\nlegend|located-at|time:2018|lPpFFU9EMr8:10161-10214",
      "subjectId": "person:the\nlegend",
      "predicate": "located-at",
      "objectId": "time:2018",
      "evidence": {
        "transcriptId": "lPpFFU9EMr8",
        "charStart": 10161,
        "charEnd": 10214,
        "timeStart": 627,
        "timeEnd": 636
      },
      "confidence": 0.4625,
      "provenance": "nlp"
    },
    "person:linda godfrey|located-at|time:2018|lPpFFU9EMr8:10181-10214": {
      "id": "person:linda godfrey|located-at|time:2018|lPpFFU9EMr8:10181-10214",
      "subjectId": "person:linda godfrey",
      "predicate": "located-at",
      "objectId": "time:2018",
      "evidence": {
        "transcriptId": "lPpFFU9EMr8",
        "charStart": 10181,
        "charEnd": 10214,
        "timeStart": 627,
        "timeEnd": 636
      },
      "confidence": 0.8,
      "provenance": "nlp"
    },
    "person:elkhorn wisconsin|said|person:danny\nmorgan|lPpFFU9EMr8:10272-10354": {
      "id": "person:elkhorn wisconsin|said|person:danny\nmorgan|lPpFFU9EMr8:10272-10354",
      "subjectId": "person:elkhorn wisconsin",
      "predicate": "said",
      "objectId": "person:danny\nmorgan",
      "evidence": {
        "transcriptId": "lPpFFU9EMr8",
        "charStart": 10272,
        "charEnd": 10354,
        "timeStart": 636,
        "timeEnd": 644
      },
      "confidence": 0.26249999999999996,
      "provenance": "nlp"
    },
    "person:the gable|located-at|time:2007|lPpFFU9EMr8:11833-11881": {
      "id": "person:the gable|located-at|time:2007|lPpFFU9EMr8:11833-11881",
      "subjectId": "person:the gable",
      "predicate": "located-at",
      "objectId": "time:2007",
      "evidence": {
        "transcriptId": "lPpFFU9EMr8",
        "charStart": 11833,
        "charEnd": 11881,
        "timeStart": 729,
        "timeEnd": 739
      },
      "confidence": 0.5125,
      "provenance": "nlp"
    },
    "person:the gable|located-at|time:2007|lPpFFU9EMr8:11844-11881": {
      "id": "person:the gable|located-at|time:2007|lPpFFU9EMr8:11844-11881",
      "subjectId": "person:the gable",
      "predicate": "located-at",
      "objectId": "time:2007",
      "evidence": {
        "transcriptId": "lPpFFU9EMr8",
        "charStart": 11844,
        "charEnd": 11881,
        "timeStart": 729,
        "timeEnd": 739
      },
      "confidence": 0.7,
      "provenance": "nlp"
    },
    "time:2012|located-at|person:rudy eugene|lPpFFU9EMr8:15256-15328": {
      "id": "time:2012|located-at|person:rudy eugene|lPpFFU9EMr8:15256-15328",
      "subjectId": "time:2012",
      "predicate": "located-at",
      "objectId": "person:rudy eugene",
      "evidence": {
        "transcriptId": "lPpFFU9EMr8",
        "charStart": 15256,
        "charEnd": 15328,
        "timeStart": 964,
        "timeEnd": 972
      },
      "confidence": 0.2,
      "provenance": "nlp"
    },
    "person:trace amounts|located-at|person:august austin|lPpFFU9EMr8:16976-17021": {
      "id": "person:trace amounts|located-at|person:august austin|lPpFFU9EMr8:16976-17021",
      "subjectId": "person:trace amounts",
      "predicate": "located-at",
      "objectId": "person:august austin",
      "evidence": {
        "transcriptId": "lPpFFU9EMr8",
        "charStart": 16976,
        "charEnd": 17021,
        "timeStart": 1074,
        "timeEnd": 1082
      },
      "confidence": 0.6375,
      "provenance": "nlp"
    }
  },
  "transcripts": {
    "nr-zETVa8mY": true,
    "AOO5a_jUOzg": true,
    "lPpFFU9EMr8": true,
    "TSZ9wPPcszo": true,
    "lLZyRA7oLik": true,
    "bAUN1GJD5BQ": true,
    "2NMBjRd8PXw": true
  }
}