{"entities":[{"id":"organization:navy","type":"organization","canonical":"Navy","aliases":[],"mentions":[{"transcriptId":"BzRR4Yg6B3w","charStart":63,"charEnd":67,"timeStart":4.48,"timeEnd":9.719000000000001},{"transcriptId":"BzRR4Yg6B3w","charStart":4430,"charEnd":4434,"timeStart":324.6,"timeEnd":328.52000000000004},{"transcriptId":"BzRR4Yg6B3w","charStart":22871,"charEnd":22875,"timeStart":1694.399,"timeEnd":1698.559},{"transcriptId":"BzRR4Yg6B3w","charStart":22975,"charEnd":22979,"timeStart":1698.559,"timeEnd":1702.72}]},{"id":"person:ed cameron","type":"person","canonical":"Ed Cameron","aliases":["Ed","his","him","he"],"mentions":[{"transcriptId":"BzRR4Yg6B3w","charStart":77,"charEnd":87,"timeStart":4.48,"timeEnd":9.719000000000001},{"transcriptId":"BzRR4Yg6B3w","charStart":319,"charEnd":321,"timeStart":18.72,"timeEnd":23.68},{"transcriptId":"BzRR4Yg6B3w","charStart":5409,"charEnd":5411,"timeStart":412.96,"timeEnd":417.75899999999996},{"transcriptId":"BzRR4Yg6B3w","charStart":6091,"charEnd":6093,"timeStart":460.24,"timeEnd":465.08},{"transcriptId":"BzRR4Yg6B3w","charStart":6181,"charEnd":6183,"timeStart":467,"timeEnd":471.52},{"transcriptId":"BzRR4Yg6B3w","charStart":6416,"charEnd":6418,"timeStart":481.159,"timeEnd":485.879},{"transcriptId":"BzRR4Yg6B3w","charStart":6796,"charEnd":6798,"timeStart":506.919,"timeEnd":511.599},{"transcriptId":"BzRR4Yg6B3w","charStart":7383,"charEnd":7385,"timeStart":548.12,"timeEnd":552.64},{"transcriptId":"BzRR4Yg6B3w","charStart":7516,"charEnd":7518,"timeStart":572.8,"timeEnd":577.279},{"transcriptId":"BzRR4Yg6B3w","charStart":8676,"charEnd":8678,"timeStart":655.8,"timeEnd":660.7199999999999},{"transcriptId":"BzRR4Yg6B3w","charStart":9066,"charEnd":9068,"timeStart":682.24,"timeEnd":685.76},{"transcriptId":"BzRR4Yg6B3w","charStart":9256,"charEnd":9258,"timeStart":708.44,"timeEnd":714},{"transcriptId":"BzRR4Yg6B3w","charStart":10333,"charEnd":10335,"timeStart":788.76,"timeEnd":794},{"transcriptId":"BzRR4Yg6B3w","charStart":11541,"charEnd":11543,"timeStart":891.04,"timeEnd":895.7199999999999},{"transcriptId":"BzRR4Yg6B3w","charStart":11734,"charEnd":11736,"timeStart":904.279,"timeEnd":909},{"transcriptId":"BzRR4Yg6B3w","charStart":12890,"charEnd":12892,"timeStart":981.959,"timeEnd":986.8},{"transcriptId":"BzRR4Yg6B3w","charStart":12944,"charEnd":12946,"timeStart":986.8,"timeEnd":991.399},{"transcriptId":"BzRR4Yg6B3w","charStart":13033,"charEnd":13035,"timeStart":991.399,"timeEnd":996.92},{"transcriptId":"BzRR4Yg6B3w","charStart":13439,"charEnd":13441,"timeStart":1018.04,"timeEnd":1022.36},{"transcriptId":"BzRR4Yg6B3w","charStart":13501,"charEnd":13503,"timeStart":1022.36,"timeEnd":1027.4},{"transcriptId":"BzRR4Yg6B3w","charStart":13589,"charEnd":13599,"timeStart":1040.36,"timeEnd":1045.1599999999999},{"transcriptId":"BzRR4Yg6B3w","charStart":13805,"charEnd":13807,"timeStart":1052.52,"timeEnd":1060.32},{"transcriptId":"BzRR4Yg6B3w","charStart":14300,"charEnd":14302,"timeStart":1089.799,"timeEnd":1095},{"transcriptId":"BzRR4Yg6B3w","charStart":14419,"charEnd":14421,"timeStart":1097.96,"timeEnd":1103.52},{"transcriptId":"BzRR4Yg6B3w","charStart":14594,"charEnd":14596,"timeStart":1111.36,"timeEnd":1118.52},{"transcriptId":"BzRR4Yg6B3w","charStart":14821,"charEnd":14823,"timeStart":1128.96,"timeEnd":1133.8400000000001},{"transcriptId":"BzRR4Yg6B3w","charStart":14968,"charEnd":14970,"timeStart":1139.32,"timeEnd":1144.12},{"transcriptId":"BzRR4Yg6B3w","charStart":15165,"charEnd":15167,"timeStart":1154.919,"timeEnd":1159.2},{"transcriptId":"BzRR4Yg6B3w","charStart":15391,"charEnd":15393,"timeStart":1167.44,"timeEnd":1172.159},{"transcriptId":"BzRR4Yg6B3w","charStart":24243,"charEnd":24253,"timeStart":1790.76,"timeEnd":1796.279},{"transcriptId":"BzRR4Yg6B3w","charStart":92,"charEnd":95,"timeStart":4.48,"timeEnd":9.719000000000001},{"transcriptId":"BzRR4Yg6B3w","charStart":9264,"charEnd":9267,"timeStart":710.959,"timeEnd":716.959},{"transcriptId":"BzRR4Yg6B3w","charStart":11551,"charEnd":11554,"timeStart":891.04,"timeEnd":895.7199999999999},{"transcriptId":"BzRR4Yg6B3w","charStart":11572,"charEnd":11575,"timeStart":891.04,"timeEnd":895.7199999999999},{"transcriptId":"BzRR4Yg6B3w","charStart":11589,"charEnd":11591,"timeStart":893.68,"timeEnd":899.16},{"transcriptId":"BzRR4Yg6B3w","charStart":13449,"charEnd":13452,"timeStart":1018.04,"timeEnd":1022.36},{"transcriptId":"BzRR4Yg6B3w","charStart":13469,"charEnd":13471,"timeStart":1020.24,"timeEnd":1024.839},{"transcriptId":"BzRR4Yg6B3w","charStart":13607,"charEnd":13610,"timeStart":1040.36,"timeEnd":1045.1599999999999},{"transcriptId":"BzRR4Yg6B3w","charStart":13634,"charEnd":13637,"timeStart":1043.28,"timeEnd":1047.319},{"transcriptId":"BzRR4Yg6B3w","charStart":13669,"charEnd":13671,"timeStart":1045.16,"timeEnd":1050.44},{"transcriptId":"BzRR4Yg6B3w","charStart":13683,"charEnd":13686,"timeStart":1045.16,"timeEnd":1050.44},{"transcriptId":"BzRR4Yg6B3w","charStart":15445,"charEnd":15447,"timeStart":1169.88,"timeEnd":1174.44},{"transcriptId":"BzRR4Yg6B3w","charStart":15464,"charEnd":15466,"timeStart":1172.159,"timeEnd":1176.3600000000001},{"transcriptId":"BzRR4Yg6B3w","charStart":15491,"charEnd":15493,"timeStart":1174.44,"timeEnd":1179.3600000000001}]},{"id":"person:duncan cameron","type":"person","canonical":"Duncan Cameron","aliases":["Duncan","his","him","he"],"mentions":[{"transcriptId":"BzRR4Yg6B3w","charStart":104,"charEnd":110,"timeStart":7.319,"timeEnd":11.48},{"transcriptId":"BzRR4Yg6B3w","charStart":4539,"charEnd":4553,"timeStart":331.08,"timeEnd":335.08},{"transcriptId":"BzRR4Yg6B3w","charStart":5416,"charEnd":5430,"timeStart":412.96,"timeEnd":417.75899999999996},{"transcriptId":"BzRR4Yg6B3w","charStart":6098,"charEnd":6112,"timeStart":462.68,"timeEnd":467},{"transcriptId":"BzRR4Yg6B3w","charStart":6423,"charEnd":6429,"timeStart":481.159,"timeEnd":485.879},{"transcriptId":"BzRR4Yg6B3w","charStart":6803,"charEnd":6809,"timeStart":509.759,"timeEnd":514},{"transcriptId":"BzRR4Yg6B3w","charStart":7390,"charEnd":7396,"timeStart":551.2,"timeEnd":554.6},{"transcriptId":"BzRR4Yg6B3w","charStart":7523,"charEnd":7537,"timeStart":572.8,"timeEnd":577.279},{"transcriptId":"BzRR4Yg6B3w","charStart":8683,"charEnd":8689,"timeStart":655.8,"timeEnd":660.7199999999999},{"transcriptId":"BzRR4Yg6B3w","charStart":8721,"charEnd":8727,"timeStart":658.56,"timeEnd":662.8},{"transcriptId":"BzRR4Yg6B3w","charStart":8830,"charEnd":8836,"timeStart":667.48,"timeEnd":672.2},{"transcriptId":"BzRR4Yg6B3w","charStart":9073,"charEnd":9079,"timeStart":682.24,"timeEnd":685.76},{"transcriptId":"BzRR4Yg6B3w","charStart":9177,"charEnd":9183,"timeStart":702.72,"timeEnd":708.44},{"transcriptId":"BzRR4Yg6B3w","charStart":9301,"charEnd":9307,"timeStart":714,"timeEnd":720.639},{"transcriptId":"BzRR4Yg6B3w","charStart":10322,"charEnd":10328,"timeStart":788.76,"timeEnd":794},{"transcriptId":"BzRR4Yg6B3w","charStart":10448,"charEnd":10454,"timeStart":801.199,"timeEnd":806.399},{"transcriptId":"BzRR4Yg6B3w","charStart":11409,"charEnd":11415,"timeStart":867.079,"timeEnd":872.199},{"transcriptId":"BzRR4Yg6B3w","charStart":11596,"charEnd":11602,"timeStart":893.68,"timeEnd":899.16},{"transcriptId":"BzRR4Yg6B3w","charStart":11743,"charEnd":11749,"timeStart":904.279,"timeEnd":909},{"transcriptId":"BzRR4Yg6B3w","charStart":12278,"charEnd":12284,"timeStart":940.68,"timeEnd":945.7589999999999},{"transcriptId":"BzRR4Yg6B3w","charStart":12320,"charEnd":12326,"timeStart":945.759,"timeEnd":950.48},{"transcriptId":"BzRR4Yg6B3w","charStart":12400,"charEnd":12406,"timeStart":950.48,"timeEnd":955.6800000000001},{"transcriptId":"BzRR4Yg6B3w","charStart":12680,"charEnd":12686,"timeStart":966.6,"timeEnd":970.6800000000001},{"transcriptId":"BzRR4Yg6B3w","charStart":12840,"charEnd":12846,"timeStart":979.04,"timeEnd":984.5999999999999},{"transcriptId":"BzRR4Yg6B3w","charStart":12975,"charEnd":12981,"timeStart":989.56,"timeEnd":995.04},{"transcriptId":"BzRR4Yg6B3w","charStart":13333,"charEnd":13339,"timeStart":1011.839,"timeEnd":1015.6},{"transcriptId":"BzRR4Yg6B3w","charStart":13486,"charEnd":13492,"timeStart":1020.24,"timeEnd":1024.839},{"transcriptId":"BzRR4Yg6B3w","charStart":13695,"charEnd":13701,"timeStart":1047.319,"timeEnd":1052.52},{"transcriptId":"BzRR4Yg6B3w","charStart":13709,"charEnd":13715,"timeStart":1047.319,"timeEnd":1052.52},{"transcriptId":"BzRR4Yg6B3w","charStart":14160,"charEnd":14166,"timeStart":1079.799,"timeEnd":1085.039},{"transcriptId":"BzRR4Yg6B3w","charStart":14378,"charEnd":14384,"timeStart":1095,"timeEnd":1101.159},{"transcriptId":"BzRR4Yg6B3w","charStart":14437,"charEnd":14443,"timeStart":1101.159,"timeEnd":1105.88},{"transcriptId":"BzRR4Yg6B3w","charStart":14785,"charEnd":14791,"timeStart":1125.24,"timeEnd":1131.24},{"transcriptId":"BzRR4Yg6B3w","charStart":14828,"charEnd":14842,"timeStart":1128.96,"timeEnd":1133.8400000000001},{"transcriptId":"BzRR4Yg6B3w","charStart":15172,"charEnd":15178,"timeStart":1154.919,"timeEnd":1159.2},{"transcriptId":"BzRR4Yg6B3w","charStart":16428,"charEnd":16442,"timeStart":1249.84,"timeEnd":1256.12},{"transcriptId":"BzRR4Yg6B3w","charStart":16466,"charEnd":16472,"timeStart":1253.6,"timeEnd":1258.84},{"transcriptId":"BzRR4Yg6B3w","charStart":18142,"charEnd":18148,"timeStart":1363.799,"timeEnd":1368.36},{"transcriptId":"BzRR4Yg6B3w","charStart":22929,"charEnd":22943,"timeStart":1696.88,"timeEnd":1701.519},{"transcriptId":"BzRR4Yg6B3w","charStart":23737,"charEnd":23743,"timeStart":1753.76,"timeEnd":1758.44},{"transcriptId":"BzRR4Yg6B3w","charStart":8751,"charEnd":8754,"timeStart":660.72,"timeEnd":664.6800000000001},{"transcriptId":"BzRR4Yg6B3w","charStart":8770,"charEnd":8773,"timeStart":660.72,"timeEnd":664.6800000000001},{"transcriptId":"BzRR4Yg6B3w","charStart":8856,"charEnd":8859,"timeStart":667.48,"timeEnd":672.2},{"transcriptId":"BzRR4Yg6B3w","charStart":8894,"charEnd":8896,"timeStart":669.839,"timeEnd":674.2790000000001},{"transcriptId":"BzRR4Yg6B3w","charStart":8902,"charEnd":8904,"timeStart":669.839,"timeEnd":674.2790000000001},{"transcriptId":"BzRR4Yg6B3w","charStart":9213,"charEnd":9215,"timeStart":705.76,"timeEnd":710.959},{"transcriptId":"BzRR4Yg6B3w","charStart":12694,"charEnd":12697,"timeStart":968.839,"timeEnd":973.1990000000001},{"transcriptId":"BzRR4Yg6B3w","charStart":13760,"charEnd":13763,"timeStart":1050.44,"timeEnd":1057.16}]},{"id":"misc:world\nwar ii","type":"misc","canonical":"World\nWar II","aliases":[],"mentions":[{"transcriptId":"BzRR4Yg6B3w","charStart":280,"charEnd":292,"timeStart":16.6,"timeEnd":23.68}]},{"id":"misc:philadelphia\nexperiment","type":"misc","canonical":"Philadelphia\nExperiment","aliases":[],"mentions":[{"transcriptId":"BzRR4Yg6B3w","charStart":839,"charEnd":862,"timeStart":53.239,"timeEnd":58.039},{"transcriptId":"BzRR4Yg6B3w","charStart":7773,"charEnd":7796,"timeStart":589.24,"timeEnd":595.6}]},{"id":"person:bill #bzrr4yg6b3w","type":"person","canonical":"Bill #BzRR4Yg6B3w","aliases":["Bill"],"mentions":[{"transcriptId":"BzRR4Yg6B3w","charStart":1269,"charEnd":1273,"timeStart":90.4,"timeEnd":94.479}]},{"id":"person:don barracuda","type":"person","canonical":"Don Barracuda","aliases":[],"mentions":[{"transcriptId":"BzRR4Yg6B3w","charStart":1380,"charEnd":1393,"timeStart":97.24,"timeEnd":102.399},{"transcriptId":"BzRR4Yg6B3w","charStart":1537,"charEnd":1550,"timeStart":106.56,"timeEnd":111.71900000000001}]},{"id":"organization:rocket","type":"organization","canonical":"Rocket","aliases":[],"mentions":[{"transcriptId":"BzRR4Yg6B3w","charStart":2549,"charEnd":2555,"timeStart":172,"timeEnd":176.48}]},{"id":"misc:world war ii","type":"misc","canonical":"World War II","aliases":[],"mentions":[{"transcriptId":"BzRR4Yg6B3w","charStart":2927,"charEnd":2939,"timeStart":217.439,"timeEnd":222.959}]},{"id":"location:united states","type":"location","canonical":"United States","aliases":["America","US"],"mentions":[{"transcriptId":"BzRR4Yg6B3w","charStart":2951,"charEnd":2964,"timeStart":217.439,"timeEnd":222.959},{"transcriptId":"BzRR4Yg6B3w","charStart":2989,"charEnd":2996,"timeStart":219.959,"timeEnd":225.28},{"transcriptId":"BzRR4Yg6B3w","charStart":3105,"charEnd":3107,"timeStart":227.36,"timeEnd":232.239},{"transcriptId":"BzRR4Yg6B3w","charStart":3709,"charEnd":3711,"timeStart":272,"timeEnd":277.199},{"transcriptId":"BzRR4Yg6B3w","charStart":3800,"charEnd":3802,"timeStart":277.199,"timeEnd":283.16},{"transcriptId":"BzRR4Yg6B3w","charStart":4001,"charEnd":4014,"timeStart":293.919,"timeEnd":298.639},{"transcriptId":"BzRR4Yg6B3w","charStart":20646,"charEnd":20648,"timeStart":1531.72,"timeEnd":1537.279},{"transcriptId":"BzRR4Yg6B3w","charStart":20715,"charEnd":20717,"timeStart":1537.279,"timeEnd":1542.2},{"transcriptId":"BzRR4Yg6B3w","charStart":20819,"charEnd":20821,"timeStart":1545,"timeEnd":1550.12},{"transcriptId":"BzRR4Yg6B3w","charStart":20927,"charEnd":20929,"timeStart":1550.12,"timeEnd":1554.1999999999998},{"transcriptId":"BzRR4Yg6B3w","charStart":2951,"charEnd":2964,"timeStart":217.439,"timeEnd":222.959},{"transcriptId":"BzRR4Yg6B3w","charStart":4001,"charEnd":4014,"timeStart":293.919,"timeEnd":298.639}]},{"id":"location:united kingdom","type":"location","canonical":"United Kingdom","aliases":["England"],"mentions":[{"transcriptId":"BzRR4Yg6B3w","charStart":3091,"charEnd":3098,"timeStart":227.36,"timeEnd":232.239}]},{"id":"misc:world war i","type":"misc","canonical":"World War I","aliases":[],"mentions":[{"transcriptId":"BzRR4Yg6B3w","charStart":3221,"charEnd":3232,"timeStart":234.4,"timeEnd":238.92000000000002}]},{"id":"person:nicola tesla","type":"person","canonical":"Nicola Tesla","aliases":["Tesla","Nicola\nTesla","he"],"mentions":[{"transcriptId":"BzRR4Yg6B3w","charStart":3233,"charEnd":3245,"timeStart":237.319,"timeEnd":241.51899999999998},{"transcriptId":"BzRR4Yg6B3w","charStart":3340,"charEnd":3345,"timeStart":241.519,"timeEnd":246.12},{"transcriptId":"BzRR4Yg6B3w","charStart":3841,"charEnd":3846,"timeStart":283.16,"timeEnd":288.32000000000005},{"transcriptId":"BzRR4Yg6B3w","charStart":8198,"charEnd":8210,"timeStart":618.24,"timeEnd":625.48},{"transcriptId":"BzRR4Yg6B3w","charStart":3351,"charEnd":3353,"timeStart":244.239,"timeEnd":248.36}]},{"id":"organization:united\nstates army","type":"organization","canonical":"United\nStates Army","aliases":[],"mentions":[{"transcriptId":"BzRR4Yg6B3w","charStart":3262,"charEnd":3280,"timeStart":237.319,"timeEnd":244.23899999999998}]},{"id":"location:germany","type":"location","canonical":"Germany","aliases":[],"mentions":[{"transcriptId":"BzRR4Yg6B3w","charStart":3591,"charEnd":3598,"timeStart":261.52,"timeEnd":269.71999999999997}]},{"id":"misc:nazi","type":"misc","canonical":"Nazi","aliases":[],"mentions":[{"transcriptId":"BzRR4Yg6B3w","charStart":3625,"charEnd":3629,"timeStart":265.8,"timeEnd":272}]},{"id":"location:russia","type":"location","canonical":"Russia","aliases":[],"mentions":[{"transcriptId":"BzRR4Yg6B3w","charStart":3698,"charEnd":3704,"timeStart":272,"timeEnd":277.199},{"transcriptId":"BzRR4Yg6B3w","charStart":3698,"charEnd":3704,"timeStart":272,"timeEnd":277.199},{"transcriptId":"BzRR4Yg6B3w","charStart":9666,"charEnd":9672,"timeStart":744.399,"timeEnd":749.88}]},{"id":"person:albert einstein","type":"person","canonical":"Albert Einstein","aliases":["Einstein","Albert\nEinstein"],"mentions":[{"transcriptId":"BzRR4Yg6B3w","charStart":3924,"charEnd":3939,"timeStart":288.32,"timeEnd":293.919},{"transcriptId":"BzRR4Yg6B3w","charStart":4078,"charEnd":4086,"timeStart":298.639,"timeEnd":302.88},{"transcriptId":"BzRR4Yg6B3w","charStart":5674,"charEnd":5689,"timeStart":431.759,"timeEnd":438}]},{"id":"person:john v norman","type":"person","canonical":"John V Norman","aliases":["John"],"mentions":[{"transcriptId":"BzRR4Yg6B3w","charStart":4387,"charEnd":4400,"timeStart":321.8,"timeEnd":326.12},{"transcriptId":"BzRR4Yg6B3w","charStart":7073,"charEnd":7077,"timeStart":526.24,"timeEnd":530.72},{"transcriptId":"BzRR4Yg6B3w","charStart":24542,"charEnd":24546,"timeStart":1812.679,"timeEnd":1818.72}]},{"id":"misc:eldridge","type":"misc","canonical":"Eldridge","aliases":[],"mentions":[{"transcriptId":"BzRR4Yg6B3w","charStart":4826,"charEnd":4834,"timeStart":352.72,"timeEnd":356.759},{"transcriptId":"BzRR4Yg6B3w","charStart":5191,"charEnd":5199,"timeStart":393.96,"timeEnd":397.35999999999996},{"transcriptId":"BzRR4Yg6B3w","charStart":22959,"charEnd":22967,"timeStart":1698.559,"timeEnd":1702.72}]},{"id":"location:virginia","type":"location","canonical":"Virginia","aliases":[],"mentions":[{"transcriptId":"BzRR4Yg6B3w","charStart":4894,"charEnd":4902,"timeStart":359.639,"timeEnd":365.36}]},{"id":"location:philadelphia","type":"location","canonical":"Philadelphia","aliases":[],"mentions":[{"transcriptId":"BzRR4Yg6B3w","charStart":5123,"charEnd":5135,"timeStart":375.16,"timeEnd":382.84000000000003},{"transcriptId":"BzRR4Yg6B3w","charStart":5214,"charEnd":5226,"timeStart":395.36,"timeEnd":399.52000000000004},{"transcriptId":"BzRR4Yg6B3w","charStart":14070,"charEnd":14082,"timeStart":1074,"timeEnd":1079.799},{"transcriptId":"BzRR4Yg6B3w","charStart":18820,"charEnd":18832,"timeStart":1404.799,"timeEnd":1409.8799999999999},{"transcriptId":"BzRR4Yg6B3w","charStart":839,"charEnd":851,"timeStart":53.239,"timeEnd":58.038999999999994},{"transcriptId":"BzRR4Yg6B3w","charStart":5123,"charEnd":5135,"timeStart":375.16,"timeEnd":382.84000000000003},{"transcriptId":"BzRR4Yg6B3w","charStart":5214,"charEnd":5226,"timeStart":395.36,"timeEnd":399.52000000000004},{"transcriptId":"BzRR4Yg6B3w","charStart":6067,"charEnd":6079,"timeStart":460.24,"timeEnd":465.08},{"transcriptId":"BzRR4Yg6B3w","charStart":6569,"charEnd":6581,"timeStart":490,"timeEnd":493.759},{"transcriptId":"BzRR4Yg6B3w","charStart":7773,"charEnd":7785,"timeStart":589.24,"timeEnd":593.519},{"transcriptId":"BzRR4Yg6B3w","charStart":7810,"charEnd":7822,"timeStart":591.36,"timeEnd":595.6},{"transcriptId":"BzRR4Yg6B3w","charStart":14070,"charEnd":14082,"timeStart":1074,"timeEnd":1079.799},{"transcriptId":"BzRR4Yg6B3w","charStart":15218,"charEnd":15230,"timeStart":1159.2,"timeEnd":1163.64},{"transcriptId":"BzRR4Yg6B3w","charStart":18581,"charEnd":18593,"timeStart":1390.64,"timeEnd":1395.0800000000002},{"transcriptId":"BzRR4Yg6B3w","charStart":18657,"charEnd":18669,"timeStart":1395.08,"timeEnd":1398.9189999999999},{"transcriptId":"BzRR4Yg6B3w","charStart":18737,"charEnd":18749,"timeStart":1400.08,"timeEnd":1403.6789999999999},{"transcriptId":"BzRR4Yg6B3w","charStart":18820,"charEnd":18832,"timeStart":1404.799,"timeEnd":1409.8799999999999},{"transcriptId":"BzRR4Yg6B3w","charStart":22175,"charEnd":22187,"timeStart":1644.32,"timeEnd":1648.32},{"transcriptId":"BzRR4Yg6B3w","charStart":22551,"charEnd":22563,"timeStart":1671.36,"timeEnd":1675.32},{"transcriptId":"BzRR4Yg6B3w","charStart":23003,"charEnd":23015,"timeStart":1701.519,"timeEnd":1705.72},{"transcriptId":"BzRR4Yg6B3w","charStart":23130,"charEnd":23142,"timeStart":1709.919,"timeEnd":1714.7990000000002},{"transcriptId":"BzRR4Yg6B3w","charStart":23465,"charEnd":23477,"timeStart":1731.08,"timeEnd":1735.399},{"transcriptId":"BzRR4Yg6B3w","charStart":25106,"charEnd":25118,"timeStart":1851.64,"timeEnd":1856.519}]},{"id":"organization:us\nnavy","type":"organization","canonical":"US\nNavy","aliases":[],"mentions":[{"transcriptId":"BzRR4Yg6B3w","charStart":5604,"charEnd":5611,"timeStart":426.639,"timeEnd":433.52000000000004}]},{"id":"misc:philadelphia experiment","type":"misc","canonical":"Philadelphia Experiment","aliases":[],"mentions":[{"transcriptId":"BzRR4Yg6B3w","charStart":6067,"charEnd":6090,"timeStart":460.24,"timeEnd":465.08},{"transcriptId":"BzRR4Yg6B3w","charStart":15218,"charEnd":15241,"timeStart":1159.2,"timeEnd":1163.64},{"transcriptId":"BzRR4Yg6B3w","charStart":18737,"charEnd":18760,"timeStart":1400.08,"timeEnd":1403.6789999999999},{"transcriptId":"BzRR4Yg6B3w","charStart":23130,"charEnd":23153,"timeStart":1709.919,"timeEnd":1714.7990000000002},{"transcriptId":"BzRR4Yg6B3w","charStart":25106,"charEnd":25129,"timeStart":1851.64,"timeEnd":1856.519}]},{"id":"organization:cameron brothers","type":"organization","canonical":"Cameron Brothers","aliases":[],"mentions":[{"transcriptId":"BzRR4Yg6B3w","charStart":6263,"charEnd":6279,"timeStart":471.52,"timeEnd":476.479}]},{"id":"location:philadelphia shipyard","type":"location","canonical":"Philadelphia Shipyard","aliases":[],"mentions":[{"transcriptId":"BzRR4Yg6B3w","charStart":6569,"charEnd":6590,"timeStart":490,"timeEnd":493.759}]},{"id":"person:van no","type":"person","canonical":"van no","aliases":[],"mentions":[{"transcriptId":"BzRR4Yg6B3w","charStart":7135,"charEnd":7141,"timeStart":530.72,"timeEnd":537.399}]},{"id":"person:van norman","type":"person","canonical":"Van Norman","aliases":[],"mentions":[{"transcriptId":"BzRR4Yg6B3w","charStart":7314,"charEnd":7324,"timeStart":544.72,"timeEnd":551.2}]},{"id":"location:long\nisland","type":"location","canonical":"Long\nIsland","aliases":[],"mentions":[{"transcriptId":"BzRR4Yg6B3w","charStart":7617,"charEnd":7628,"timeStart":577.279,"timeEnd":584.24}]},{"id":"misc:multiverse","type":"misc","canonical":"Multiverse","aliases":[],"mentions":[{"transcriptId":"BzRR4Yg6B3w","charStart":8964,"charEnd":8974,"timeStart":674.279,"timeEnd":680.079}]},{"id":"person:edward cameron","type":"person","canonical":"Edward Cameron","aliases":["Edward","Edward\nCameron","he","him"],"mentions":[{"transcriptId":"BzRR4Yg6B3w","charStart":8983,"charEnd":8989,"timeStart":677.24,"timeEnd":682.24},{"transcriptId":"BzRR4Yg6B3w","charStart":18100,"charEnd":18114,"timeStart":1359.36,"timeEnd":1366.4399999999998},{"transcriptId":"BzRR4Yg6B3w","charStart":19220,"charEnd":19234,"timeStart":1431.52,"timeEnd":1436.84},{"transcriptId":"BzRR4Yg6B3w","charStart":22792,"charEnd":22806,"timeStart":1690.24,"timeEnd":1694.3990000000001},{"transcriptId":"BzRR4Yg6B3w","charStart":22919,"charEnd":22925,"timeStart":1696.88,"timeEnd":1701.519},{"transcriptId":"BzRR4Yg6B3w","charStart":24202,"charEnd":24216,"timeStart":1787.88,"timeEnd":1793.7600000000002},{"transcriptId":"BzRR4Yg6B3w","charStart":24301,"charEnd":24315,"timeStart":1793.76,"timeEnd":1798.44},{"transcriptId":"BzRR4Yg6B3w","charStart":24444,"charEnd":24458,"timeStart":1805.08,"timeEnd":1810.1999999999998},{"transcriptId":"BzRR4Yg6B3w","charStart":4528,"charEnd":4534,"timeStart":331.08,"timeEnd":335.08},{"transcriptId":"BzRR4Yg6B3w","charStart":9015,"charEnd":9017,"timeStart":677.24,"timeEnd":682.24},{"transcriptId":"BzRR4Yg6B3w","charStart":22842,"charEnd":22845,"timeStart":1692.12,"timeEnd":1696.8799999999999}]},{"id":"location:west russia","type":"location","canonical":"West Russia","aliases":[],"mentions":[{"transcriptId":"BzRR4Yg6B3w","charStart":9661,"charEnd":9672,"timeStart":744.399,"timeEnd":749.88}]},{"id":"location:china","type":"location","canonical":"China","aliases":[],"mentions":[{"transcriptId":"BzRR4Yg6B3w","charStart":9677,"charEnd":9682,"timeStart":744.399,"timeEnd":749.88},{"transcriptId":"BzRR4Yg6B3w","charStart":9677,"charEnd":9682,"timeStart":744.399,"timeEnd":749.88}]},{"id":"location:earth","type":"location","canonical":"Earth","aliases":[],"mentions":[{"transcriptId":"BzRR4Yg6B3w","charStart":9701,"charEnd":9706,"timeStart":747.76,"timeEnd":752.4399999999999}]},{"id":"organization:utopia society","type":"organization","canonical":"Utopia Society","aliases":[],"mentions":[{"transcriptId":"BzRR4Yg6B3w","charStart":10473,"charEnd":10487,"timeStart":801.199,"timeEnd":806.399}]},{"id":"location:paradise","type":"location","canonical":"Paradise","aliases":[],"mentions":[{"transcriptId":"BzRR4Yg6B3w","charStart":11296,"charEnd":11304,"timeStart":858.88,"timeEnd":864.24}]},{"id":"location:barren plains","type":"location","canonical":"Barren Plains","aliases":[],"mentions":[{"transcriptId":"BzRR4Yg6B3w","charStart":12069,"charEnd":12082,"timeStart":927.16,"timeEnd":932}]},{"id":"person:al be","type":"person","canonical":"Al Be","aliases":["Al","his","he"],"mentions":[{"transcriptId":"BzRR4Yg6B3w","charStart":14585,"charEnd":14587,"timeStart":1111.36,"timeEnd":1118.52},{"transcriptId":"BzRR4Yg6B3w","charStart":14707,"charEnd":14709,"timeStart":1120.799,"timeEnd":1125.24},{"transcriptId":"BzRR4Yg6B3w","charStart":16111,"charEnd":16113,"timeStart":1233.039,"timeEnd":1237.32},{"transcriptId":"BzRR4Yg6B3w","charStart":16287,"charEnd":16289,"timeStart":1242.039,"timeEnd":1246.8799999999999},{"transcriptId":"BzRR4Yg6B3w","charStart":16480,"charEnd":16482,"timeStart":1253.6,"timeEnd":1258.84},{"transcriptId":"BzRR4Yg6B3w","charStart":16524,"charEnd":16526,"timeStart":1258.84,"timeEnd":1263.84},{"transcriptId":"BzRR4Yg6B3w","charStart":17160,"charEnd":17162,"timeStart":1297.72,"timeEnd":1302.159},{"transcriptId":"BzRR4Yg6B3w","charStart":17582,"charEnd":17584,"timeStart":1326.24,"timeEnd":1330.88},{"transcriptId":"BzRR4Yg6B3w","charStart":18086,"charEnd":18088,"timeStart":1359.36,"timeEnd":1363.799},{"transcriptId":"BzRR4Yg6B3w","charStart":18212,"charEnd":18214,"timeStart":1366.44,"timeEnd":1371.64},{"transcriptId":"BzRR4Yg6B3w","charStart":18263,"charEnd":18265,"timeStart":1371.64,"timeEnd":1376.3200000000002},{"transcriptId":"BzRR4Yg6B3w","charStart":18626,"charEnd":18628,"timeStart":1392.679,"timeEnd":1396.799},{"transcriptId":"BzRR4Yg6B3w","charStart":20525,"charEnd":20527,"timeStart":1523.44,"timeEnd":1529.159},{"transcriptId":"BzRR4Yg6B3w","charStart":22248,"charEnd":22253,"timeStart":1648.32,"timeEnd":1654.039},{"transcriptId":"BzRR4Yg6B3w","charStart":22255,"charEnd":22257,"timeStart":1648.32,"timeEnd":1654.039},{"transcriptId":"BzRR4Yg6B3w","charStart":22476,"charEnd":22478,"timeStart":1664.679,"timeEnd":1671.3600000000001},{"transcriptId":"BzRR4Yg6B3w","charStart":22617,"charEnd":22619,"timeStart":1675.32,"timeEnd":1682},{"transcriptId":"BzRR4Yg6B3w","charStart":22640,"charEnd":22642,"timeStart":1679.72,"timeEnd":1684.919},{"transcriptId":"BzRR4Yg6B3w","charStart":22846,"charEnd":22848,"timeStart":1692.12,"timeEnd":1696.8799999999999},{"transcriptId":"BzRR4Yg6B3w","charStart":23580,"charEnd":23582,"timeStart":1737.679,"timeEnd":1744.6000000000001},{"transcriptId":"BzRR4Yg6B3w","charStart":23785,"charEnd":23787,"timeStart":1755.48,"timeEnd":1760.3600000000001},{"transcriptId":"BzRR4Yg6B3w","charStart":24485,"charEnd":24487,"timeStart":1807.159,"timeEnd":1812.679},{"transcriptId":"BzRR4Yg6B3w","charStart":24534,"charEnd":24536,"timeStart":1812.679,"timeEnd":1818.72},{"transcriptId":"BzRR4Yg6B3w","charStart":25044,"charEnd":25046,"timeStart":1846.72,"timeEnd":1851.64},{"transcriptId":"BzRR4Yg6B3w","charStart":25417,"charEnd":25419,"timeStart":1875.639,"timeEnd":1882.1999999999998},{"transcriptId":"BzRR4Yg6B3w","charStart":25599,"charEnd":25601,"timeStart":1887.2,"timeEnd":1892.44},{"transcriptId":"BzRR4Yg6B3w","charStart":25732,"charEnd":25734,"timeStart":1896.039,"timeEnd":1900.919},{"transcriptId":"BzRR4Yg6B3w","charStart":26655,"charEnd":26657,"timeStart":1951.2,"timeEnd":1955.519},{"transcriptId":"BzRR4Yg6B3w","charStart":26703,"charEnd":26705,"timeStart":1953.08,"timeEnd":1957.76},{"transcriptId":"BzRR4Yg6B3w","charStart":26868,"charEnd":26870,"timeStart":1962.639,"timeEnd":1966.9189999999999},{"transcriptId":"BzRR4Yg6B3w","charStart":27087,"charEnd":27089,"timeStart":1976.88,"timeEnd":1981.48},{"transcriptId":"BzRR4Yg6B3w","charStart":16317,"charEnd":16320,"timeStart":1244.64,"timeEnd":1248.44},{"transcriptId":"BzRR4Yg6B3w","charStart":17187,"charEnd":17189,"timeStart":1300.24,"timeEnd":1304.88},{"transcriptId":"BzRR4Yg6B3w","charStart":22648,"charEnd":22650,"timeStart":1679.72,"timeEnd":1684.919},{"transcriptId":"BzRR4Yg6B3w","charStart":22696,"charEnd":22698,"timeStart":1682,"timeEnd":1687.519},{"transcriptId":"BzRR4Yg6B3w","charStart":22709,"charEnd":22711,"timeStart":1682,"timeEnd":1687.519},{"transcriptId":"BzRR4Yg6B3w","charStart":22744,"charEnd":22746,"timeStart":1684.919,"timeEnd":1690.24},{"transcriptId":"BzRR4Yg6B3w","charStart":22777,"charEnd":22779,"timeStart":1687.519,"timeEnd":1692.1200000000001},{"transcriptId":"BzRR4Yg6B3w","charStart":23622,"charEnd":23624,"timeStart":1741.039,"timeEnd":1749.12},{"transcriptId":"BzRR4Yg6B3w","charStart":23669,"charEnd":23671,"timeStart":1744.6,"timeEnd":1750.7199999999998},{"transcriptId":"BzRR4Yg6B3w","charStart":25477,"charEnd":25479,"timeStart":1879.559,"timeEnd":1885.84},{"transcriptId":"BzRR4Yg6B3w","charStart":25627,"charEnd":25630,"timeStart":1890.24,"timeEnd":1894},{"transcriptId":"BzRR4Yg6B3w","charStart":25777,"charEnd":25780,"timeStart":1898.48,"timeEnd":1903.2},{"transcriptId":"BzRR4Yg6B3w","charStart":26673,"charEnd":26675,"timeStart":1951.2,"timeEnd":1955.519},{"transcriptId":"BzRR4Yg6B3w","charStart":26695,"charEnd":26697,"timeStart":1953.08,"timeEnd":1957.76},{"transcriptId":"BzRR4Yg6B3w","charStart":26741,"charEnd":26743,"timeStart":1955.519,"timeEnd":1960.24},{"transcriptId":"BzRR4Yg6B3w","charStart":26786,"charEnd":26789,"timeStart":1957.76,"timeEnd":1962.639},{"transcriptId":"BzRR4Yg6B3w","charStart":26890,"charEnd":26892,"timeStart":1964.76,"timeEnd":1968.96}]},{"id":"person:christopher nolan","type":"person","canonical":"Christopher Nolan","aliases":[],"mentions":[{"transcriptId":"BzRR4Yg6B3w","charStart":15078,"charEnd":15095,"timeStart":1145.32,"timeEnd":1148.84}]},{"id":"location:new york","type":"location","canonical":"New York","aliases":[],"mentions":[{"transcriptId":"BzRR4Yg6B3w","charStart":16128,"charEnd":16136,"timeStart":1233.039,"timeEnd":1237.32},{"transcriptId":"BzRR4Yg6B3w","charStart":22663,"charEnd":22671,"timeStart":1679.72,"timeEnd":1684.919},{"transcriptId":"BzRR4Yg6B3w","charStart":16128,"charEnd":16136,"timeStart":1233.039,"timeEnd":1237.32},{"transcriptId":"BzRR4Yg6B3w","charStart":22663,"charEnd":22671,"timeStart":1679.72,"timeEnd":1684.919},{"transcriptId":"BzRR4Yg6B3w","charStart":23047,"charEnd":23055,"timeStart":1702.72,"timeEnd":1707.64}]},{"id":"person:preston nichols","type":"person","canonical":"Preston Nichols","aliases":["Nichols","Preston","Preston\nNichols","he","his","him"],"mentions":[{"transcriptId":"BzRR4Yg6B3w","charStart":16145,"charEnd":16160,"timeStart":1235.12,"timeEnd":1239.2399999999998},{"transcriptId":"BzRR4Yg6B3w","charStart":16338,"charEnd":16345,"timeStart":1246.88,"timeEnd":1249.8400000000001},{"transcriptId":"BzRR4Yg6B3w","charStart":16934,"charEnd":16941,"timeStart":1281.32,"timeEnd":1285.48},{"transcriptId":"BzRR4Yg6B3w","charStart":17071,"charEnd":17078,"timeStart":1293.4,"timeEnd":1297.72},{"transcriptId":"BzRR4Yg6B3w","charStart":17626,"charEnd":17641,"timeStart":1328.32,"timeEnd":1335.0800000000002},{"transcriptId":"BzRR4Yg6B3w","charStart":17669,"charEnd":17676,"timeStart":1333.36,"timeEnd":1338.52},{"transcriptId":"BzRR4Yg6B3w","charStart":17713,"charEnd":17728,"timeStart":1335.08,"timeEnd":1340.3999999999999},{"transcriptId":"BzRR4Yg6B3w","charStart":17895,"charEnd":17902,"timeStart":1347.88,"timeEnd":1352.3200000000002},{"transcriptId":"BzRR4Yg6B3w","charStart":20532,"charEnd":20547,"timeStart":1523.44,"timeEnd":1529.159},{"transcriptId":"BzRR4Yg6B3w","charStart":25974,"charEnd":25989,"timeStart":1909.72,"timeEnd":1915.32},{"transcriptId":"BzRR4Yg6B3w","charStart":16191,"charEnd":16193,"timeStart":1237.32,"timeEnd":1242.039},{"transcriptId":"BzRR4Yg6B3w","charStart":16385,"charEnd":16387,"timeStart":1248.44,"timeEnd":1253.6000000000001},{"transcriptId":"BzRR4Yg6B3w","charStart":16415,"charEnd":16418,"timeStart":1249.84,"timeEnd":1256.12},{"transcriptId":"BzRR4Yg6B3w","charStart":16958,"charEnd":16960,"timeStart":1284.12,"timeEnd":1288.4799999999998},{"transcriptId":"BzRR4Yg6B3w","charStart":17650,"charEnd":17652,"timeStart":1330.88,"timeEnd":1335.0800000000002},{"transcriptId":"BzRR4Yg6B3w","charStart":17709,"charEnd":17712,"timeStart":1335.08,"timeEnd":1340.3999999999999},{"transcriptId":"BzRR4Yg6B3w","charStart":17767,"charEnd":17769,"timeStart":1338.52,"timeEnd":1342.84},{"transcriptId":"BzRR4Yg6B3w","charStart":17810,"charEnd":17812,"timeStart":1340.4,"timeEnd":1345.3200000000002}]},{"id":"organization:hbo","type":"organization","canonical":"HBO","aliases":[],"mentions":[{"transcriptId":"BzRR4Yg6B3w","charStart":18337,"charEnd":18340,"timeStart":1376.32,"timeEnd":1380.08}]},{"id":"person:robert per","type":"person","canonical":"Robert Per","aliases":["Robert\nPer"],"mentions":[{"transcriptId":"BzRR4Yg6B3w","charStart":19055,"charEnd":19065,"timeStart":1418.6,"timeEnd":1425.799}]},{"id":"organization:black ops","type":"organization","canonical":"Black Ops","aliases":[],"mentions":[{"transcriptId":"BzRR4Yg6B3w","charStart":19307,"charEnd":19316,"timeStart":1436.84,"timeEnd":1442.8799999999999}]},{"id":"person:d cameron","type":"person","canonical":"D Cameron","aliases":["D\nCameron"],"mentions":[{"transcriptId":"BzRR4Yg6B3w","charStart":19966,"charEnd":19975,"timeStart":1482.679,"timeEnd":1493.6}]},{"id":"organization:ar","type":"organization","canonical":"AR","aliases":[],"mentions":[{"transcriptId":"BzRR4Yg6B3w","charStart":20435,"charEnd":20437,"timeStart":1519.48,"timeEnd":1523.44}]},{"id":"misc:c","type":"misc","canonical":"C","aliases":[],"mentions":[{"transcriptId":"BzRR4Yg6B3w","charStart":21098,"charEnd":21099,"timeStart":1563.32,"timeEnd":1570.08}]},{"id":"person:green #bzrr4yg6b3w","type":"person","canonical":"Green #BzRR4Yg6B3w","aliases":["Green"],"mentions":[{"transcriptId":"BzRR4Yg6B3w","charStart":21301,"charEnd":21306,"timeStart":1577.76,"timeEnd":1583.799}]},{"id":"organization:ufo","type":"organization","canonical":"UFO","aliases":[],"mentions":[{"transcriptId":"BzRR4Yg6B3w","charStart":23201,"charEnd":23204,"timeStart":1711.72,"timeEnd":1717.64}]},{"id":"person:carl allen","type":"person","canonical":"Carl Allen","aliases":[],"mentions":[{"transcriptId":"BzRR4Yg6B3w","charStart":23215,"charEnd":23225,"timeStart":1714.799,"timeEnd":1719.799}]},{"id":"organization:al","type":"organization","canonical":"Al","aliases":[],"mentions":[{"transcriptId":"BzRR4Yg6B3w","charStart":24271,"charEnd":24273,"timeStart":1790.76,"timeEnd":1796.279}]},{"id":"person:cameron alexander cameron","type":"person","canonical":"Cameron Alexander Cameron","aliases":["Cameron Alexander\nCameron"],"mentions":[{"transcriptId":"BzRR4Yg6B3w","charStart":24379,"charEnd":24404,"timeStart":1798.44,"timeEnd":1807.159}]},{"id":"organization:office of naval research","type":"organization","canonical":"Office of Naval Research","aliases":[],"mentions":[{"transcriptId":"BzRR4Yg6B3w","charStart":25061,"charEnd":25085,"timeStart":1849.6,"timeEnd":1853.519}]},{"id":"organization:alc","type":"organization","canonical":"ALC","aliases":[],"mentions":[{"transcriptId":"BzRR4Yg6B3w","charStart":26484,"charEnd":26487,"timeStart":1940.159,"timeEnd":1945}]},{"id":"misc:once upon a time","type":"misc","canonical":"Once Upon a Time","aliases":[],"mentions":[{"transcriptId":"BzRR4Yg6B3w","charStart":27183,"charEnd":27199,"timeStart":1983.96,"timeEnd":1989.279}]},{"id":"misc:my","type":"misc","canonical":"My","aliases":[],"mentions":[{"transcriptId":"BzRR4Yg6B3w","charStart":27639,"charEnd":27641,"timeStart":2014.279,"timeEnd":2019.08}]},{"id":"person:bob lazar","type":"person","canonical":"Bob Lazar","aliases":[],"mentions":[{"transcriptId":"BzRR4Yg6B3w","charStart":27930,"charEnd":27939,"timeStart":2035,"timeEnd":2040.6}]},{"id":"person:phil schneider","type":"person","canonical":"Phil Schneider","aliases":[],"mentions":[{"transcriptId":"BzRR4Yg6B3w","charStart":27943,"charEnd":27957,"timeStart":2035,"timeEnd":2040.6}]},{"id":"person:david #bzrr4yg6b3w","type":"person","canonical":"David #BzRR4Yg6B3w","aliases":["David"],"mentions":[{"transcriptId":"BzRR4Yg6B3w","charStart":27961,"charEnd":27966,"timeStart":2038.039,"timeEnd":2042.96}]},{"id":"person:aj #bzrr4yg6b3w","type":"person","canonical":"AJ #BzRR4Yg6B3w","aliases":["AJ"],"mentions":[{"transcriptId":"BzRR4Yg6B3w","charStart":28745,"charEnd":28747,"timeStart":2098.28,"timeEnd":2102.6800000000003}]},{"id":"misc:bia scara","type":"misc","canonical":"Bia Scara","aliases":[],"mentions":[{"transcriptId":"BzRR4Yg6B3w","charStart":31172,"charEnd":31181,"timeStart":2250.64,"timeEnd":2260.04}]},{"id":"person:stanley #bzrr4yg6b3w","type":"person","canonical":"Stanley #BzRR4Yg6B3w","aliases":["Stanley"],"mentions":[{"transcriptId":"BzRR4Yg6B3w","charStart":31494,"charEnd":31501,"timeStart":2297.52,"timeEnd":2304.72}]},{"id":"person:sid #bzrr4yg6b3w","type":"person","canonical":"Sid #BzRR4Yg6B3w","aliases":["Sid"],"mentions":[{"transcriptId":"BzRR4Yg6B3w","charStart":31846,"charEnd":31849,"timeStart":2355.2,"timeEnd":2363.1189999999997}]},{"id":"misc:the","type":"misc","canonical":"The","aliases":[],"mentions":[{"transcriptId":"BzRR4Yg6B3w","charStart":31893,"charEnd":31896,"timeStart":2357.92,"timeEnd":2363.119}]},{"id":"person:c #bzrr4yg6b3w","type":"person","canonical":"C #BzRR4Yg6B3w","aliases":["C"],"mentions":[{"transcriptId":"BzRR4Yg6B3w","charStart":31904,"charEnd":31905,"timeStart":2357.92,"timeEnd":2363.119}]},{"id":"time:1977","type":"time","canonical":"1977","aliases":[],"mentions":[{"transcriptId":"BzRR4Yg6B3w","charStart":792,"charEnd":796,"timeStart":49.719,"timeEnd":55.039}]},{"id":"time:1939","type":"time","canonical":"1939","aliases":[],"mentions":[{"transcriptId":"BzRR4Yg6B3w","charStart":3586,"charEnd":3590,"timeStart":261.52,"timeEnd":269.71999999999997}]},{"id":"time:1942","type":"time","canonical":"1942","aliases":[],"mentions":[{"transcriptId":"BzRR4Yg6B3w","charStart":3620,"charEnd":3624,"timeStart":265.8,"timeEnd":272}]},{"id":"time:1919","type":"time","canonical":"1919","aliases":[],"mentions":[{"transcriptId":"BzRR4Yg6B3w","charStart":3919,"charEnd":3923,"timeStart":288.32,"timeEnd":293.919}]},{"id":"time:1943","type":"time","canonical":"1943","aliases":[],"mentions":[{"transcriptId":"BzRR4Yg6B3w","charStart":4344,"charEnd":4348,"timeStart":318.84,"timeEnd":324.59999999999997},{"transcriptId":"BzRR4Yg6B3w","charStart":6011,"charEnd":6015,"timeStart":454.44,"timeEnd":460.24},{"transcriptId":"BzRR4Yg6B3w","charStart":7304,"charEnd":7308,"timeStart":544.72,"timeEnd":551.2},{"transcriptId":"BzRR4Yg6B3w","charStart":23637,"charEnd":23641,"timeStart":1741.039,"timeEnd":1749.12},{"transcriptId":"BzRR4Yg6B3w","charStart":25157,"charEnd":25161,"timeStart":1853.519,"timeEnd":1859.36}]},{"id":"time:1983","type":"time","canonical":"1983","aliases":[],"mentions":[{"transcriptId":"BzRR4Yg6B3w","charStart":7193,"charEnd":7197,"timeStart":533.72,"timeEnd":539.399},{"transcriptId":"BzRR4Yg6B3w","charStart":7269,"charEnd":7273,"timeStart":542,"timeEnd":548.12},{"transcriptId":"BzRR4Yg6B3w","charStart":23645,"charEnd":23649,"timeStart":1741.039,"timeEnd":1749.12},{"transcriptId":"BzRR4Yg6B3w","charStart":24651,"charEnd":24655,"timeStart":1823,"timeEnd":1828.88}]},{"id":"time:1987","type":"time","canonical":"1987","aliases":[],"mentions":[{"transcriptId":"BzRR4Yg6B3w","charStart":9172,"charEnd":9176,"timeStart":702.72,"timeEnd":708.44}]},{"id":"time:1916","type":"time","canonical":"1916","aliases":[],"mentions":[{"transcriptId":"BzRR4Yg6B3w","charStart":14625,"charEnd":14629,"timeStart":1115,"timeEnd":1120.799}]},{"id":"time:1985","type":"time","canonical":"1985","aliases":[],"mentions":[{"transcriptId":"BzRR4Yg6B3w","charStart":16106,"charEnd":16110,"timeStart":1229.32,"timeEnd":1235.12}]},{"id":"time:1988","type":"time","canonical":"1988","aliases":[],"mentions":[{"transcriptId":"BzRR4Yg6B3w","charStart":18231,"charEnd":18235,"timeStart":1368.36,"timeEnd":1374.6789999999999}]},{"id":"time:1990","type":"time","canonical":"1990","aliases":[],"mentions":[{"transcriptId":"BzRR4Yg6B3w","charStart":20134,"charEnd":20138,"timeStart":1500,"timeEnd":1505.679}]},{"id":"time:1989","type":"time","canonical":"1989","aliases":[],"mentions":[{"transcriptId":"BzRR4Yg6B3w","charStart":22274,"charEnd":22278,"timeStart":1651.72,"timeEnd":1657.44}]},{"id":"time:1927","type":"time","canonical":"1927","aliases":[],"mentions":[{"transcriptId":"BzRR4Yg6B3w","charStart":22675,"charEnd":22679,"timeStart":1682,"timeEnd":1687.519}]},{"id":"time:2043","type":"time","canonical":"2043","aliases":[],"mentions":[{"transcriptId":"BzRR4Yg6B3w","charStart":23683,"charEnd":23687,"timeStart":1744.6,"timeEnd":1750.7199999999998}]},{"id":"time:1957","type":"time","canonical":"1957","aliases":[],"mentions":[{"transcriptId":"BzRR4Yg6B3w","charStart":24619,"charEnd":24623,"timeStart":1820.08,"timeEnd":1825.96}]},{"id":"time:2000","type":"time","canonical":"2000","aliases":[],"mentions":[{"transcriptId":"BzRR4Yg6B3w","charStart":25448,"charEnd":25452,"timeStart":1875.639,"timeEnd":1882.1999999999998}]},{"id":"time:2005","type":"time","canonical":"2005","aliases":[],"mentions":[{"transcriptId":"BzRR4Yg6B3w","charStart":25485,"charEnd":25489,"timeStart":1879.559,"timeEnd":1885.84}]},{"id":"time:2015","type":"time","canonical":"2015","aliases":[],"mentions":[{"transcriptId":"BzRR4Yg6B3w","charStart":25495,"charEnd":25499,"timeStart":1882.2,"timeEnd":1887.2}]},{"id":"time:2011","type":"time","canonical":"2011","aliases":[],"mentions":[{"transcriptId":"BzRR4Yg6B3w","charStart":25521,"charEnd":25525,"timeStart":1882.2,"timeEnd":1887.2}]},{"id":"organization:tesla","type":"organization","canonical":"Tesla","aliases":[],"mentions":[{"transcriptId":"BzRR4Yg6B3w","charStart":3240,"charEnd":3245,"timeStart":237.319,"timeEnd":241.51899999999998},{"transcriptId":"BzRR4Yg6B3w","charStart":3340,"charEnd":3345,"timeStart":241.519,"timeEnd":246.12},{"transcriptId":"BzRR4Yg6B3w","charStart":3395,"charEnd":3400,"timeStart":246.12,"timeEnd":251},{"transcriptId":"BzRR4Yg6B3w","charStart":3526,"charEnd":3531,"timeStart":253.2,"timeEnd":258.13},{"transcriptId":"BzRR4Yg6B3w","charStart":3841,"charEnd":3846,"timeStart":283.16,"timeEnd":288.32000000000005},{"transcriptId":"BzRR4Yg6B3w","charStart":4068,"charEnd":4073,"timeStart":298.639,"timeEnd":302.88},{"transcriptId":"BzRR4Yg6B3w","charStart":8205,"charEnd":8210,"timeStart":620.88,"timeEnd":625.48}]},{"id":"location:america","type":"location","canonical":"America","aliases":[],"mentions":[{"transcriptId":"BzRR4Yg6B3w","charStart":2989,"charEnd":2996,"timeStart":219.959,"timeEnd":225.28}]},{"id":"location:europe","type":"location","canonical":"Europe","aliases":[],"mentions":[{"transcriptId":"BzRR4Yg6B3w","charStart":3660,"charEnd":3666,"timeStart":269.72,"timeEnd":274.72}]},{"id":"location:africa","type":"location","canonical":"Africa","aliases":[],"mentions":[{"transcriptId":"BzRR4Yg6B3w","charStart":3673,"charEnd":3679,"timeStart":269.72,"timeEnd":274.72}]}],"relationships":[{"id":"person:al be|visited|location:new york|BzRR4Yg6B3w:16111-16136","subjectId":"person:al be","predicate":"visited","objectId":"location:new york","evidence":{"transcriptId":"BzRR4Yg6B3w","charStart":16111,"charEnd":16136,"timeStart":1233.039,"timeEnd":1237.32},"confidence":0.875,"provenance":"nlp"},{"id":"person:al be|born-in|location:new york|BzRR4Yg6B3w:22640-22671","subjectId":"person:al be","predicate":"born-in","objectId":"location:new york","evidence":{"transcriptId":"BzRR4Yg6B3w","charStart":22640,"charEnd":22671,"timeStart":1679.72,"timeEnd":1684.919},"confidence":0.825,"provenance":"nlp"},{"id":"person:al be|born-in|location:new york|BzRR4Yg6B3w:22648-22671","subjectId":"person:al be","predicate":"born-in","objectId":"location:new york","evidence":{"transcriptId":"BzRR4Yg6B3w","charStart":22648,"charEnd":22671,"timeStart":1679.72,"timeEnd":1684.919},"confidence":0.8916666666666666,"provenance":"nlp"},{"id":"person:al be|said|time:1927|BzRR4Yg6B3w:22675-22711","subjectId":"person:al be","predicate":"said","objectId":"time:1927","evidence":{"transcriptId":"BzRR4Yg6B3w","charStart":22675,"charEnd":22711,"timeStart":1682,"timeEnd":1687.519},"confidence":0.75,"provenance":"nlp"},{"id":"person:al be|said|person:john v norman|BzRR4Yg6B3w:24534-24546","subjectId":"person:al be","predicate":"said","objectId":"person:john v norman","evidence":{"transcriptId":"BzRR4Yg6B3w","charStart":24534,"charEnd":24546,"timeStart":1812.679,"timeEnd":1818.72},"confidence":0.9,"provenance":"nlp"},{"id":"person:al be|said|time:2000|BzRR4Yg6B3w:25417-25452","subjectId":"person:al be","predicate":"said","objectId":"time:2000","evidence":{"transcriptId":"BzRR4Yg6B3w","charStart":25417,"charEnd":25452,"timeStart":1875.639,"timeEnd":1882.1999999999998},"confidence":0.7583333333333333,"provenance":"nlp"},{"id":"person:al be|said|time:2005|BzRR4Yg6B3w:25477-25489","subjectId":"person:al be","predicate":"said","objectId":"time:2005","evidence":{"transcriptId":"BzRR4Yg6B3w","charStart":25477,"charEnd":25489,"timeStart":1879.559,"timeEnd":1885.84},"confidence":0.9,"provenance":"nlp"}]}